[{"airlineIata":"8U","arrivalIata":"MJI","departureIata":"AMM","codeshares":null,"flightNumber":"603","arrivalTime":"20:00:00","departureTime":"16:00:00"},{"airlineIata":"A3","arrivalIata":"ATH","departureIata":"AMM","codeshares":null,"flightNumber":"941","arrivalTime":"07:10:00","departureTime":"05:00:00"},{"airlineIata":"AF","arrivalIata":"CDG","departureIata":"AMM","codeshares":[{"airline_code":"DL","flight_number":"8429"},{"airline_code":"KL","flight_number":"2239"}],"flightNumber":"487","arrivalTime":"05:30:00","departureTime":"01:25:00"},{"airlineIata":"AH","arrivalIata":"ALG","departureIata":"AMM","codeshares":null,"flightNumber":"4065","arrivalTime":"13:45:00","departureTime":"10:30:00"},{"airlineIata":"AZ","arrivalIata":"FCO","departureIata":"AMM","codeshares":[{"airline_code":"DL","flight_number":"6700"},{"airline_code":"JU","flight_number":"8665"}],"flightNumber":"821","arrivalTime":"07:00:00","departureTime":"04:20:00"},{"airlineIata":"BA","arrivalIata":"LHR","departureIata":"AMM","codeshares":null,"flightNumber":"146","arrivalTime":"10:45:00","departureTime":"07:05:00"},{"airlineIata":"U8","arrivalIata":"LCA","departureIata":"AMM","codeshares":null,"flightNumber":"701","arrivalTime":"13:45:00","departureTime":"12:30:00"},{"airlineIata":"EK","arrivalIata":"DXB","departureIata":"AMM","codeshares":null,"flightNumber":"2516","arrivalTime":"01:55:00","departureTime":"21:55:00"},{"airlineIata":"EK","arrivalIata":"DXB","departureIata":"AMM","codeshares":[{"airline_code":"MH","flight_number":"4526"},{"airline_code":"QF","flight_number":"8902"}],"flightNumber":"902","arrivalTime":"15:10:00","departureTime":"11:10:00"},{"airlineIata":"EK","arrivalIata":"DXB","departureIata":"AMM","codeshares":[{"airline_code":"QF","flight_number":"8904"}],"flightNumber":"904","arrivalTime":"21:15:00","departureTime":"17:15:00"},{"airlineIata":"EK","arrivalIata":"DXB","departureIata":"AMM","codeshares":[{"airline_code":"MH","flight_number":"4524"},{"airline_code":"QF","flight_number":"8906"}],"flightNumber":"906","arrivalTime":"06:15:00","departureTime":"02:15:00"},{"airlineIata":"EY","arrivalIata":"AUH","departureIata":"AMM","codeshares":[{"airline_code":"9W","flight_number":"6438"},{"airline_code":"HM","flight_number":"5225"},{"airline_code":"KQ","flight_number":"5531"},{"airline_code":"MH","flight_number":"5282"},{"airline_code":"PK","flight_number":"4512"},{"airline_code":"SA","flight_number":"2237"},{"airline_code":"UL","flight_number":"2512"},{"airline_code":"VA","flight_number":"7121"}],"flightNumber":"512","arrivalTime":"09:10:00","departureTime":"05:00:00"},{"airlineIata":"EY","arrivalIata":"AUH","departureIata":"AMM","codeshares":[{"airline_code":"9W","flight_number":"6439"},{"airline_code":"HM","flight_number":"5227"},{"airline_code":"KE","flight_number":"7906"},{"airline_code":"OZ","flight_number":"6988"},{"airline_code":"PK","flight_number":"4514"},{"airline_code":"UL","flight_number":"2514"},{"airline_code":"VA","flight_number":"7000"}],"flightNumber":"514","arrivalTime":"19:05:00","departureTime":"14:55:00"},{"airlineIata":"FT","arrivalIata":"HBE","departureIata":"AMM","codeshares":null,"flightNumber":"822","arrivalTime":"11:30:00","departureTime":"10:00:00"},{"airlineIata":"FZ","arrivalIata":"DXB","departureIata":"AMM","codeshares":null,"flightNumber":"144","arrivalTime":"02:20:00","departureTime":"22:10:00"},{"airlineIata":"FZ","arrivalIata":"DXB","departureIata":"AMM","codeshares":null,"flightNumber":"148","arrivalTime":"14:10:00","departureTime":"10:00:00"},{"airlineIata":"FZ","arrivalIata":"DWC","departureIata":"AMM","codeshares":null,"flightNumber":"5142","arrivalTime":"19:05:00","departureTime":"15:00:00"},{"airlineIata":"FZ","arrivalIata":"DXB","departureIata":"AMM","codeshares":null,"flightNumber":"8144","arrivalTime":"04:15:00","departureTime":"00:05:00"},{"airlineIata":"G9","arrivalIata":"SHJ","departureIata":"AMM","codeshares":null,"flightNumber":"330","arrivalTime":"01:35:00","departureTime":"21:35:00"},{"airlineIata":"G9","arrivalIata":"SHJ","departureIata":"AMM","codeshares":null,"flightNumber":"338","arrivalTime":"15:15:00","departureTime":"11:15:00"},{"airlineIata":"GF","arrivalIata":"BAH","departureIata":"AMM","codeshares":[{"airline_code":"RJ","flight_number":"3301"}],"flightNumber":"972","arrivalTime":"14:50:00","departureTime":"12:25:00"},{"airlineIata":"GF","arrivalIata":"BAH","departureIata":"AMM","codeshares":null,"flightNumber":"974","arrivalTime":"00:10:00","departureTime":"21:45:00"},{"airlineIata":"IA","arrivalIata":"BGW","departureIata":"AMM","codeshares":null,"flightNumber":"164","arrivalTime":"19:00:00","departureTime":"16:30:00"},{"airlineIata":"IA","arrivalIata":"BSR","departureIata":"AMM","codeshares":null,"flightNumber":"168","arrivalTime":"16:00:00","departureTime":"13:00:00"},{"airlineIata":"IA","arrivalIata":"EBL","departureIata":"AMM","codeshares":null,"flightNumber":"178","arrivalTime":"18:00:00","departureTime":"15:15:00"},{"airlineIata":"IA","arrivalIata":"ISU","departureIata":"AMM","codeshares":null,"flightNumber":"182","arrivalTime":"21:00:00","departureTime":"18:30:00"},{"airlineIata":"J9","arrivalIata":"KWI","departureIata":"AMM","codeshares":null,"flightNumber":"239","arrivalTime":"00:20:00","departureTime":"21:55:00"},{"airlineIata":"J9","arrivalIata":"KWI","departureIata":"AMM","codeshares":null,"flightNumber":"241","arrivalTime":"12:30:00","departureTime":"10:05:00"},{"airlineIata":"R5","arrivalIata":"BGW","departureIata":"AMM","codeshares":null,"flightNumber":"611","arrivalTime":"13:30:00","departureTime":"12:00:00"},{"airlineIata":"R5","arrivalIata":"KWI","departureIata":"AMM","codeshares":null,"flightNumber":"621","arrivalTime":"09:25:00","departureTime":"07:20:00"},{"airlineIata":"R5","arrivalIata":"BAH","departureIata":"AMM","codeshares":null,"flightNumber":"645","arrivalTime":"17:40:00","departureTime":"15:00:00"},{"airlineIata":"R5","arrivalIata":"SSH","departureIata":"AMM","codeshares":null,"flightNumber":"815","arrivalTime":"10:00:00","departureTime":"09:00:00"},{"airlineIata":"KU","arrivalIata":"KWI","departureIata":"AMM","codeshares":null,"flightNumber":"562","arrivalTime":"16:55:00","departureTime":"14:35:00"},{"airlineIata":"KU","arrivalIata":"KWI","departureIata":"AMM","codeshares":null,"flightNumber":"564","arrivalTime":"00:35:00","departureTime":"22:15:00"},{"airlineIata":"LH","arrivalIata":"FRA","departureIata":"AMM","codeshares":[{"airline_code":"AC","flight_number":"9265"},{"airline_code":"UA","flight_number":"9151"}],"flightNumber":"693","arrivalTime":"06:20:00","departureTime":"02:35:00"},{"airlineIata":"LN","arrivalIata":"MJI","departureIata":"AMM","codeshares":null,"flightNumber":"283","arrivalTime":"17:55:00","departureTime":"15:15:00"},{"airlineIata":"LN","arrivalIata":"BEN","departureIata":"AMM","codeshares":null,"flightNumber":"285","arrivalTime":"16:30:00","departureTime":"14:30:00"},{"airlineIata":"ME","arrivalIata":"BEY","departureIata":"AMM","codeshares":[{"airline_code":"RJ","flight_number":"3752"}],"flightNumber":"311","arrivalTime":"11:25:00","departureTime":"10:15:00"},{"airlineIata":"ME","arrivalIata":"BEY","departureIata":"AMM","codeshares":[{"airline_code":"RJ","flight_number":"3754"}],"flightNumber":"313","arrivalTime":"20:00:00","departureTime":"18:50:00"},{"airlineIata":"ME","arrivalIata":"BEY","departureIata":"AMM","codeshares":[{"airline_code":"RJ","flight_number":"3756"}],"flightNumber":"315","arrivalTime":"16:25:00","departureTime":"15:15:00"},{"airlineIata":"MS","arrivalIata":"CAI","departureIata":"AMM","codeshares":null,"flightNumber":"702","arrivalTime":"20:45:00","departureTime":"20:15:00"},{"airlineIata":"MS","arrivalIata":"CAI","departureIata":"AMM","codeshares":null,"flightNumber":"708","arrivalTime":"15:50:00","departureTime":"15:20:00"},{"airlineIata":"MS","arrivalIata":"CAI","departureIata":"AMM","codeshares":null,"flightNumber":"720","arrivalTime":"10:35:00","departureTime":"10:05:00"},{"airlineIata":"MS","arrivalIata":"CAI","departureIata":"AMM","codeshares":null,"flightNumber":"740","arrivalTime":"06:30:00","departureTime":"06:00:00"},{"airlineIata":"SM","arrivalIata":"HBE","departureIata":"AMM","codeshares":null,"flightNumber":"212","arrivalTime":"09:15:00","departureTime":"08:30:00"},{"airlineIata":"SM","arrivalIata":"HMB","departureIata":"AMM","codeshares":null,"flightNumber":"214","arrivalTime":"19:45:00","departureTime":"19:15:00"},{"airlineIata":"NP","arrivalIata":"SSH","departureIata":"AMM","codeshares":null,"flightNumber":"322","arrivalTime":"15:50:00","departureTime":"14:50:00"},{"airlineIata":"OS","arrivalIata":"VIE","departureIata":"AMM","codeshares":[{"airline_code":"LH","flight_number":"6411"},{"airline_code":"UA","flight_number":"9816"}],"flightNumber":"854","arrivalTime":"19:15:00","departureTime":"16:20:00"},{"airlineIata":"PC","arrivalIata":"ESB","departureIata":"AMM","codeshares":null,"flightNumber":"4657","arrivalTime":"03:30:00","departureTime":"01:35:00"},{"airlineIata":"PC","arrivalIata":"AYT","departureIata":"AMM","codeshares":null,"flightNumber":"4801","arrivalTime":"05:45:00","departureTime":"03:55:00"},{"airlineIata":"PC","arrivalIata":"ESB","departureIata":"AMM","codeshares":null,"flightNumber":"681","arrivalTime":"17:00:00","departureTime":"14:10:00"},{"airlineIata":"PS","arrivalIata":"KBP","departureIata":"AMM","codeshares":null,"flightNumber":"762","arrivalTime":"07:55:00","departureTime":"04:25:00"},{"airlineIata":"9P","arrivalIata":"EBL","departureIata":"AMM","codeshares":null,"flightNumber":"123","arrivalTime":"15:50:00","departureTime":"14:10:00"},{"airlineIata":"9P","arrivalIata":"DMM","departureIata":"AMM","codeshares":null,"flightNumber":"203","arrivalTime":"16:10:00","departureTime":"13:55:00"},{"airlineIata":"9P","arrivalIata":"JED","departureIata":"AMM","codeshares":null,"flightNumber":"211","arrivalTime":"09:55:00","departureTime":"07:55:00"},{"airlineIata":"9P","arrivalIata":"RUH","departureIata":"AMM","codeshares":null,"flightNumber":"237","arrivalTime":"17:40:00","departureTime":"15:45:00"},{"airlineIata":"9P","arrivalIata":"TBS","departureIata":"AMM","codeshares":null,"flightNumber":"265","arrivalTime":"00:50:00","departureTime":"21:10:00"},{"airlineIata":"9P","arrivalIata":"KWI","departureIata":"AMM","codeshares":null,"flightNumber":"301","arrivalTime":"23:45:00","departureTime":"21:45:00"},{"airlineIata":"9P","arrivalIata":"KWI","departureIata":"AMM","codeshares":null,"flightNumber":"309","arrivalTime":"21:20:00","departureTime":"19:20:00"},{"airlineIata":"9P","arrivalIata":"SSH","departureIata":"AMM","codeshares":null,"flightNumber":"601","arrivalTime":"10:20:00","departureTime":"09:15:00"},{"airlineIata":"QR","arrivalIata":"DOH","departureIata":"AMM","codeshares":null,"flightNumber":"3201","arrivalTime":"11:00:00","departureTime":"08:20:00"},{"airlineIata":"QR","arrivalIata":"DOH","departureIata":"AMM","codeshares":null,"flightNumber":"3215","arrivalTime":"10:55:00","departureTime":"07:50:00"},{"airlineIata":"QR","arrivalIata":"DOH","departureIata":"AMM","codeshares":null,"flightNumber":"3219","arrivalTime":"01:20:00","departureTime":"22:20:00"},{"airlineIata":"QR","arrivalIata":"DOH","departureIata":"AMM","codeshares":null,"flightNumber":"3221","arrivalTime":"01:25:00","departureTime":"22:20:00"},{"airlineIata":"QR","arrivalIata":"DOH","departureIata":"AMM","codeshares":null,"flightNumber":"3223","arrivalTime":"10:25:00","departureTime":"07:20:00"},{"airlineIata":"QR","arrivalIata":"DOH","departureIata":"AMM","codeshares":null,"flightNumber":"3225","arrivalTime":"01:25:00","departureTime":"22:20:00"},{"airlineIata":"QR","arrivalIata":"DOH","departureIata":"AMM","codeshares":null,"flightNumber":"3227","arrivalTime":"10:30:00","departureTime":"07:25:00"},{"airlineIata":"QR","arrivalIata":"DOH","departureIata":"AMM","codeshares":null,"flightNumber":"3229","arrivalTime":"10:30:00","departureTime":"07:25:00"},{"airlineIata":"QR","arrivalIata":"DOH","departureIata":"AMM","codeshares":null,"flightNumber":"3235","arrivalTime":"10:20:00","departureTime":"07:20:00"},{"airlineIata":"QR","arrivalIata":"DOH","departureIata":"AMM","codeshares":null,"flightNumber":"3245","arrivalTime":"12:00:00","departureTime":"08:55:00"},{"airlineIata":"QR","arrivalIata":"DOH","departureIata":"AMM","codeshares":[{"airline_code":"RJ","flight_number":"3801"}],"flightNumber":"401","arrivalTime":"23:55:00","departureTime":"21:15:00"},{"airlineIata":"QR","arrivalIata":"DOH","departureIata":"AMM","codeshares":[{"airline_code":"RJ","flight_number":"3803"}],"flightNumber":"403","arrivalTime":"15:15:00","departureTime":"12:35:00"},{"airlineIata":"E5","arrivalIata":"HBE","departureIata":"AMM","codeshares":null,"flightNumber":"522","arrivalTime":"19:25:00","departureTime":"17:45:00"},{"airlineIata":"RL","arrivalIata":"NJF","departureIata":"AMM","codeshares":null,"flightNumber":"400","arrivalTime":"14:45:00","departureTime":"13:00:00"},{"airlineIata":"RL","arrivalIata":"CAI","departureIata":"AMM","codeshares":null,"flightNumber":"601","arrivalTime":"12:15:00","departureTime":"12:00:00"},{"airlineIata":"RJ","arrivalIata":"FCO","departureIata":"AMM","codeshares":null,"flightNumber":"101","arrivalTime":"13:20:00","departureTime":"10:30:00"},{"airlineIata":"RJ","arrivalIata":"CAI","departureIata":"AMM","codeshares":null,"flightNumber":"1032","arrivalTime":null,"departureTime":null},{"airlineIata":"RJ","arrivalIata":"MST","departureIata":"AMM","codeshares":null,"flightNumber":"1033","arrivalTime":null,"departureTime":null},{"airlineIata":"RJ","arrivalIata":"BCN","departureIata":"AMM","codeshares":[{"airline_code":"IB","flight_number":"7862"}],"flightNumber":"107","arrivalTime":"14:30:00","departureTime":"10:30:00"},{"airlineIata":"RJ","arrivalIata":"MAD","departureIata":"AMM","codeshares":[{"airline_code":"IB","flight_number":"7860"}],"flightNumber":"109","arrivalTime":"11:40:00","departureTime":"07:10:00"},{"airlineIata":"RJ","arrivalIata":"LHR","departureIata":"AMM","codeshares":[{"airline_code":"AA","flight_number":"7191"}],"flightNumber":"111","arrivalTime":"15:25:00","departureTime":"12:00:00"},{"airlineIata":"RJ","arrivalIata":"MST","departureIata":"AMM","codeshares":null,"flightNumber":"1135","arrivalTime":null,"departureTime":null},{"airlineIata":"RJ","arrivalIata":"CDG","departureIata":"AMM","codeshares":[{"airline_code":"AA","flight_number":"7195"}],"flightNumber":"117","arrivalTime":"11:15:00","departureTime":"07:10:00"},{"airlineIata":"RJ","arrivalIata":"TXL","departureIata":"AMM","codeshares":[{"airline_code":"AB","flight_number":"5501"}],"flightNumber":"121","arrivalTime":"13:45:00","departureTime":"10:15:00"},{"airlineIata":"RJ","arrivalIata":"MUC","departureIata":"AMM","codeshares":[{"airline_code":"AB","flight_number":"5503"}],"flightNumber":"123","arrivalTime":"13:20:00","departureTime":"10:15:00"},{"airlineIata":"RJ","arrivalIata":"DOH","departureIata":"AMM","codeshares":null,"flightNumber":"1240","arrivalTime":null,"departureTime":null},{"airlineIata":"RJ","arrivalIata":"DOH","departureIata":"AMM","codeshares":null,"flightNumber":"1244","arrivalTime":null,"departureTime":null},{"airlineIata":"RJ","arrivalIata":"FRA","departureIata":"AMM","codeshares":[{"airline_code":"AA","flight_number":"7197"},{"airline_code":"AB","flight_number":"5505"}],"flightNumber":"125","arrivalTime":"14:05:00","departureTime":"10:20:00"},{"airlineIata":"RJ","arrivalIata":"EBL","departureIata":"AMM","codeshares":null,"flightNumber":"1250","arrivalTime":null,"departureTime":null},{"airlineIata":"RJ","arrivalIata":"BGW","departureIata":"AMM","codeshares":null,"flightNumber":"1261","arrivalTime":null,"departureTime":null},{"airlineIata":"RJ","arrivalIata":"VIE","departureIata":"AMM","codeshares":[{"airline_code":"AB","flight_number":"5507"}],"flightNumber":"127","arrivalTime":"09:45:00","departureTime":"06:55:00"},{"airlineIata":"RJ","arrivalIata":"OTP","departureIata":"AMM","codeshares":null,"flightNumber":"1270","arrivalTime":null,"departureTime":null},{"airlineIata":"RJ","arrivalIata":"CAI","departureIata":"AMM","codeshares":null,"flightNumber":"1271","arrivalTime":null,"departureTime":null},{"airlineIata":"RJ","arrivalIata":"HKG","departureIata":"AMM","codeshares":null,"flightNumber":"1280","arrivalTime":null,"departureTime":null},{"airlineIata":"RJ","arrivalIata":"TLV","departureIata":"AMM","codeshares":null,"flightNumber":"1290","arrivalTime":null,"departureTime":null},{"airlineIata":"RJ","arrivalIata":"ATH","departureIata":"AMM","codeshares":null,"flightNumber":"131","arrivalTime":"18:10:00","departureTime":"15:45:00"},{"airlineIata":"RJ","arrivalIata":"LCA","departureIata":"AMM","codeshares":null,"flightNumber":"133","arrivalTime":"10:30:00","departureTime":"09:15:00"},{"airlineIata":"RJ","arrivalIata":"AMS","departureIata":"AMM","codeshares":null,"flightNumber":"151","arrivalTime":"11:35:00","departureTime":"07:35:00"},{"airlineIata":"RJ","arrivalIata":"GVA","departureIata":"AMM","codeshares":null,"flightNumber":"153","arrivalTime":"10:55:00","departureTime":"07:25:00"},{"airlineIata":"RJ","arrivalIata":"ESB","departureIata":"AMM","codeshares":null,"flightNumber":"161","arrivalTime":"10:55:00","departureTime":"09:00:00"},{"airlineIata":"RJ","arrivalIata":"IST","departureIata":"AMM","codeshares":[{"airline_code":"TK","flight_number":"8876"}],"flightNumber":"163","arrivalTime":"03:05:00","departureTime":"00:45:00"},{"airlineIata":"RJ","arrivalIata":"IST","departureIata":"AMM","codeshares":[{"airline_code":"TK","flight_number":"8878"}],"flightNumber":"165","arrivalTime":"13:40:00","departureTime":"11:20:00"},{"airlineIata":"RJ","arrivalIata":"IST","departureIata":"AMM","codeshares":[{"airline_code":"TK","flight_number":"8880"}],"flightNumber":"167","arrivalTime":"19:50:00","departureTime":"17:30:00"},{"airlineIata":"RJ","arrivalIata":"DME","departureIata":"AMM","codeshares":[{"airline_code":"S7","flight_number":"4082"}],"flightNumber":"177","arrivalTime":"14:35:00","departureTime":"10:15:00"},{"airlineIata":"RJ","arrivalIata":"KUL","departureIata":"AMM","codeshares":[{"airline_code":"MH","flight_number":"9044"}],"flightNumber":"184","arrivalTime":"16:55:00","departureTime":"02:25:00"},{"airlineIata":"RJ","arrivalIata":"MED","departureIata":"AMM","codeshares":null,"flightNumber":"2002","arrivalTime":"03:45:00","departureTime":"01:00:00"},{"airlineIata":"RJ","arrivalIata":"MED","departureIata":"AMM","codeshares":null,"flightNumber":"2004","arrivalTime":"11:45:00","departureTime":"09:00:00"},{"airlineIata":"RJ","arrivalIata":"MED","departureIata":"AMM","codeshares":null,"flightNumber":"2006","arrivalTime":"09:00:00","departureTime":"06:15:00"},{"airlineIata":"RJ","arrivalIata":"MED","departureIata":"AMM","codeshares":null,"flightNumber":"2008","arrivalTime":"10:00:00","departureTime":"07:15:00"},{"airlineIata":"RJ","arrivalIata":"MED","departureIata":"AMM","codeshares":null,"flightNumber":"2012","arrivalTime":"10:05:00","departureTime":"07:20:00"},{"airlineIata":"RJ","arrivalIata":"JED","departureIata":"AMM","codeshares":null,"flightNumber":"2030","arrivalTime":"10:05:00","departureTime":"07:00:00"},{"airlineIata":"RJ","arrivalIata":"JED","departureIata":"AMM","codeshares":null,"flightNumber":"2032","arrivalTime":"09:00:00","departureTime":"05:55:00"},{"airlineIata":"RJ","arrivalIata":"JED","departureIata":"AMM","codeshares":null,"flightNumber":"2034","arrivalTime":"09:30:00","departureTime":"06:25:00"},{"airlineIata":"RJ","arrivalIata":"JED","departureIata":"AMM","codeshares":null,"flightNumber":"2042","arrivalTime":"09:30:00","departureTime":"06:25:00"},{"airlineIata":"RJ","arrivalIata":"JED","departureIata":"AMM","codeshares":null,"flightNumber":"2122","arrivalTime":null,"departureTime":null},{"airlineIata":"RJ","arrivalIata":"JED","departureIata":"AMM","codeshares":null,"flightNumber":"2500","arrivalTime":null,"departureTime":null},{"airlineIata":"RJ","arrivalIata":"JED","departureIata":"AMM","codeshares":null,"flightNumber":"2502","arrivalTime":null,"departureTime":null},{"airlineIata":"RJ","arrivalIata":"JFK","departureIata":"AMM","codeshares":null,"flightNumber":"261","arrivalTime":null,"departureTime":null},{"airlineIata":"RJ","arrivalIata":"JED","departureIata":"AMM","codeshares":null,"flightNumber":"2610","arrivalTime":null,"departureTime":null},{"airlineIata":"RJ","arrivalIata":"MED","departureIata":"AMM","codeshares":null,"flightNumber":"2620","arrivalTime":null,"departureTime":null},{"airlineIata":"RJ","arrivalIata":"MED","departureIata":"AMM","codeshares":null,"flightNumber":"2622","arrivalTime":null,"departureTime":null},{"airlineIata":"RJ","arrivalIata":"ORD","departureIata":"AMM","codeshares":[{"airline_code":"AA","flight_number":"7201"}],"flightNumber":"263","arrivalTime":"16:15:00","departureTime":"11:25:00"},{"airlineIata":"RJ","arrivalIata":"MED","departureIata":"AMM","codeshares":null,"flightNumber":"2650","arrivalTime":null,"departureTime":null},{"airlineIata":"RJ","arrivalIata":"MED","departureIata":"AMM","codeshares":null,"flightNumber":"2652","arrivalTime":null,"departureTime":null},{"airlineIata":"RJ","arrivalIata":"DTW","departureIata":"AMM","codeshares":[{"airline_code":"AA","flight_number":"7203"}],"flightNumber":"267","arrivalTime":"08:00:00","departureTime":"02:50:00"},{"airlineIata":"RJ","arrivalIata":"MED","departureIata":"AMM","codeshares":null,"flightNumber":"2678","arrivalTime":null,"departureTime":null},{"airlineIata":"RJ","arrivalIata":"MED","departureIata":"AMM","codeshares":null,"flightNumber":"2686","arrivalTime":null,"departureTime":null},{"airlineIata":"RJ","arrivalIata":"YUL","departureIata":"AMM","codeshares":null,"flightNumber":"269","arrivalTime":"07:10:00","departureTime":"02:55:00"},{"airlineIata":"RJ","arrivalIata":"AQJ","departureIata":"AMM","codeshares":[{"airline_code":"AA","flight_number":"7205"}],"flightNumber":"300","arrivalTime":"07:40:00","departureTime":"06:45:00"},{"airlineIata":"RJ","arrivalIata":"AQJ","departureIata":"AMM","codeshares":[{"airline_code":"AA","flight_number":"7207"}],"flightNumber":"302","arrivalTime":"22:10:00","departureTime":"21:15:00"},{"airlineIata":"RJ","arrivalIata":"AQJ","departureIata":"AMM","codeshares":[{"airline_code":"AA","flight_number":"7183"}],"flightNumber":"304","arrivalTime":"17:15:00","departureTime":"16:20:00"},{"airlineIata":"RJ","arrivalIata":"CAI","departureIata":"AMM","codeshares":null,"flightNumber":"32","arrivalTime":null,"departureTime":null},{"airlineIata":"RJ","arrivalIata":"TLV","departureIata":"AMM","codeshares":null,"flightNumber":"3340","arrivalTime":null,"departureTime":null},{"airlineIata":"RJ","arrivalIata":"TLV","departureIata":"AMM","codeshares":null,"flightNumber":"340","arrivalTime":"21:25:00","departureTime":"20:40:00"},{"airlineIata":"RJ","arrivalIata":"TLV","departureIata":"AMM","codeshares":null,"flightNumber":"342","arrivalTime":"07:30:00","departureTime":"06:45:00"},{"airlineIata":"RJ","arrivalIata":"BEY","departureIata":"AMM","codeshares":null,"flightNumber":"401","arrivalTime":"06:55:00","departureTime":"05:00:00"},{"airlineIata":"RJ","arrivalIata":"BEY","departureIata":"AMM","codeshares":null,"flightNumber":"403","arrivalTime":"12:25:00","departureTime":"10:30:00"},{"airlineIata":"RJ","arrivalIata":"BEY","departureIata":"AMM","codeshares":[{"airline_code":"ME","flight_number":"3315"}],"flightNumber":"405","arrivalTime":"19:35:00","departureTime":"17:40:00"},{"airlineIata":"RJ","arrivalIata":"BEY","departureIata":"AMM","codeshares":[{"airline_code":"ME","flight_number":"3317"}],"flightNumber":"407","arrivalTime":"22:25:00","departureTime":"20:30:00"},{"airlineIata":"RJ","arrivalIata":"CAI","departureIata":"AMM","codeshares":null,"flightNumber":"501","arrivalTime":"08:30:00","departureTime":"08:00:00"},{"airlineIata":"RJ","arrivalIata":"CAI","departureIata":"AMM","codeshares":null,"flightNumber":"503","arrivalTime":"12:20:00","departureTime":"11:50:00"},{"airlineIata":"RJ","arrivalIata":"CAI","departureIata":"AMM","codeshares":null,"flightNumber":"505","arrivalTime":"19:15:00","departureTime":"18:45:00"},{"airlineIata":"RJ","arrivalIata":"CAI","departureIata":"AMM","codeshares":null,"flightNumber":"507","arrivalTime":"00:45:00","departureTime":"23:15:00"},{"airlineIata":"RJ","arrivalIata":"KRT","departureIata":"AMM","codeshares":null,"flightNumber":"510","arrivalTime":"03:55:00","departureTime":"00:55:00"},{"airlineIata":"RJ","arrivalIata":"BCN","departureIata":"AMM","codeshares":null,"flightNumber":"5107","arrivalTime":"06:20:00","departureTime":"02:20:00"},{"airlineIata":"RJ","arrivalIata":"MAD","departureIata":"AMM","codeshares":null,"flightNumber":"5109","arrivalTime":"01:40:00","departureTime":"21:10:00"},{"airlineIata":"RJ","arrivalIata":"LHR","departureIata":"AMM","codeshares":null,"flightNumber":"5111","arrivalTime":"19:30:00","departureTime":"15:55:00"},{"airlineIata":"RJ","arrivalIata":"LHR","departureIata":"AMM","codeshares":null,"flightNumber":"5113","arrivalTime":"10:55:00","departureTime":"07:30:00"},{"airlineIata":"RJ","arrivalIata":"CDG","departureIata":"AMM","codeshares":null,"flightNumber":"5117","arrivalTime":"14:05:00","departureTime":"10:00:00"},{"airlineIata":"RJ","arrivalIata":"ATH","departureIata":"AMM","codeshares":null,"flightNumber":"5129","arrivalTime":"18:30:00","departureTime":"16:05:00"},{"airlineIata":"RJ","arrivalIata":"ATH","departureIata":"AMM","codeshares":null,"flightNumber":"5131","arrivalTime":"09:40:00","departureTime":"07:15:00"},{"airlineIata":"RJ","arrivalIata":"LCA","departureIata":"AMM","codeshares":null,"flightNumber":"5133","arrivalTime":"11:15:00","departureTime":"10:00:00"},{"airlineIata":"RJ","arrivalIata":"LCA","departureIata":"AMM","codeshares":null,"flightNumber":"5135","arrivalTime":"00:15:00","departureTime":"23:00:00"},{"airlineIata":"RJ","arrivalIata":"LCA","departureIata":"AMM","codeshares":null,"flightNumber":"5137","arrivalTime":"00:45:00","departureTime":"23:30:00"},{"airlineIata":"RJ","arrivalIata":"ZRH","departureIata":"AMM","codeshares":null,"flightNumber":"5153","arrivalTime":"09:20:00","departureTime":"06:00:00"},{"airlineIata":"RJ","arrivalIata":"ZRH","departureIata":"AMM","codeshares":null,"flightNumber":"5155","arrivalTime":"09:05:00","departureTime":"05:45:00"},{"airlineIata":"RJ","arrivalIata":"IST","departureIata":"AMM","codeshares":null,"flightNumber":"5165","arrivalTime":null,"departureTime":null},{"airlineIata":"RJ","arrivalIata":"ALG","departureIata":"AMM","codeshares":null,"flightNumber":"517","arrivalTime":"12:00:00","departureTime":"09:20:00"},{"airlineIata":"RJ","arrivalIata":"IST","departureIata":"AMM","codeshares":null,"flightNumber":"5175","arrivalTime":"04:35:00","departureTime":"02:15:00"},{"airlineIata":"RJ","arrivalIata":"ORD","departureIata":"AMM","codeshares":null,"flightNumber":"5210","arrivalTime":"11:00:00","departureTime":"06:30:00"},{"airlineIata":"RJ","arrivalIata":"ORD","departureIata":"AMM","codeshares":null,"flightNumber":"5222","arrivalTime":"11:50:00","departureTime":"06:45:00"},{"airlineIata":"RJ","arrivalIata":"ORD","departureIata":"AMM","codeshares":null,"flightNumber":"5250","arrivalTime":"11:00:00","departureTime":"06:30:00"},{"airlineIata":"RJ","arrivalIata":"DXB","departureIata":"AMM","codeshares":null,"flightNumber":"5300","arrivalTime":"01:30:00","departureTime":"21:30:00"},{"airlineIata":"RJ","arrivalIata":"CAI","departureIata":"AMM","codeshares":null,"flightNumber":"5501","arrivalTime":"08:30:00","departureTime":"08:00:00"},{"airlineIata":"RJ","arrivalIata":"CAI","departureIata":"AMM","codeshares":null,"flightNumber":"5503","arrivalTime":"23:40:00","departureTime":"23:10:00"},{"airlineIata":"RJ","arrivalIata":"CAI","departureIata":"AMM","codeshares":null,"flightNumber":"5505","arrivalTime":"07:50:00","departureTime":"07:20:00"},{"airlineIata":"RJ","arrivalIata":"TUN","departureIata":"AMM","codeshares":null,"flightNumber":"551","arrivalTime":"12:20:00","departureTime":"10:30:00"},{"airlineIata":"RJ","arrivalIata":"DOH","departureIata":"AMM","codeshares":null,"flightNumber":"5533","arrivalTime":"04:15:00","departureTime":"01:45:00"},{"airlineIata":"RJ","arrivalIata":"DXB","departureIata":"AMM","codeshares":null,"flightNumber":"5541","arrivalTime":"11:45:00","departureTime":"07:45:00"},{"airlineIata":"RJ","arrivalIata":"FRA","departureIata":"AMM","codeshares":null,"flightNumber":"5551","arrivalTime":"18:45:00","departureTime":"15:00:00"},{"airlineIata":"RJ","arrivalIata":"CDG","departureIata":"AMM","codeshares":null,"flightNumber":"5557","arrivalTime":"06:05:00","departureTime":"02:00:00"},{"airlineIata":"RJ","arrivalIata":"AUH","departureIata":"AMM","codeshares":null,"flightNumber":"5562","arrivalTime":"00:40:00","departureTime":"20:30:00"},{"airlineIata":"RJ","arrivalIata":"AUH","departureIata":"AMM","codeshares":null,"flightNumber":"5566","arrivalTime":"03:15:00","departureTime":"23:05:00"},{"airlineIata":"RJ","arrivalIata":"DOH","departureIata":"AMM","codeshares":null,"flightNumber":"5570","arrivalTime":"01:50:00","departureTime":"23:20:00"},{"airlineIata":"RJ","arrivalIata":"DOH","departureIata":"AMM","codeshares":null,"flightNumber":"5572","arrivalTime":null,"departureTime":null},{"airlineIata":"RJ","arrivalIata":"DOH","departureIata":"AMM","codeshares":null,"flightNumber":"5574","arrivalTime":null,"departureTime":null},{"airlineIata":"RJ","arrivalIata":"DOH","departureIata":"AMM","codeshares":null,"flightNumber":"5600","arrivalTime":"05:50:00","departureTime":"02:20:00"},{"airlineIata":"RJ","arrivalIata":"DXB","departureIata":"AMM","codeshares":null,"flightNumber":"5608","arrivalTime":"04:00:00","departureTime":"23:59:00"},{"airlineIata":"RJ","arrivalIata":"DXB","departureIata":"AMM","codeshares":null,"flightNumber":"5618","arrivalTime":"02:15:00","departureTime":"22:15:00"},{"airlineIata":"RJ","arrivalIata":"AUH","departureIata":"AMM","codeshares":null,"flightNumber":"5620","arrivalTime":"00:45:00","departureTime":"20:00:00"},{"airlineIata":"RJ","arrivalIata":"AUH","departureIata":"AMM","codeshares":null,"flightNumber":"5622","arrivalTime":"06:20:00","departureTime":"02:10:00"},{"airlineIata":"RJ","arrivalIata":"AAN","departureIata":"AMM","codeshares":null,"flightNumber":"5632","arrivalTime":"23:30:00","departureTime":"19:40:00"},{"airlineIata":"RJ","arrivalIata":"DOH","departureIata":"AMM","codeshares":null,"flightNumber":"5646","arrivalTime":"02:55:00","departureTime":"00:25:00"},{"airlineIata":"RJ","arrivalIata":"DOH","departureIata":"AMM","codeshares":null,"flightNumber":"5660","arrivalTime":"02:05:00","departureTime":"23:35:00"},{"airlineIata":"RJ","arrivalIata":"DOH","departureIata":"AMM","codeshares":null,"flightNumber":"5662","arrivalTime":"01:45:00","departureTime":"23:15:00"},{"airlineIata":"RJ","arrivalIata":"DXB","departureIata":"AMM","codeshares":null,"flightNumber":"5664","arrivalTime":"02:00:00","departureTime":"22:00:00"},{"airlineIata":"RJ","arrivalIata":"AUH","departureIata":"AMM","codeshares":null,"flightNumber":"5666","arrivalTime":"05:10:00","departureTime":"01:00:00"},{"airlineIata":"RJ","arrivalIata":"AUH","departureIata":"AMM","codeshares":null,"flightNumber":"5668","arrivalTime":"11:10:00","departureTime":"07:00:00"},{"airlineIata":"RJ","arrivalIata":"JED","departureIata":"AMM","codeshares":null,"flightNumber":"5700","arrivalTime":"04:45:00","departureTime":"02:35:00"},{"airlineIata":"RJ","arrivalIata":"JED","departureIata":"AMM","codeshares":null,"flightNumber":"5704","arrivalTime":"03:50:00","departureTime":"01:40:00"},{"airlineIata":"RJ","arrivalIata":"JED","departureIata":"AMM","codeshares":null,"flightNumber":"5706","arrivalTime":"05:00:00","departureTime":"02:50:00"},{"airlineIata":"RJ","arrivalIata":"DOH","departureIata":"AMM","codeshares":null,"flightNumber":"5722","arrivalTime":"04:30:00","departureTime":"02:00:00"},{"airlineIata":"RJ","arrivalIata":"DOH","departureIata":"AMM","codeshares":null,"flightNumber":"5724","arrivalTime":"04:30:00","departureTime":"02:00:00"},{"airlineIata":"RJ","arrivalIata":"RUH","departureIata":"AMM","codeshares":null,"flightNumber":"5732","arrivalTime":"00:40:00","departureTime":"22:30:00"},{"airlineIata":"RJ","arrivalIata":"DMM","departureIata":"AMM","codeshares":null,"flightNumber":"5770","arrivalTime":"11:15:00","departureTime":"09:00:00"},{"airlineIata":"RJ","arrivalIata":"DMM","departureIata":"AMM","codeshares":null,"flightNumber":"5778","arrivalTime":"07:25:00","departureTime":"05:10:00"},{"airlineIata":"RJ","arrivalIata":"DMM","departureIata":"AMM","codeshares":null,"flightNumber":"5780","arrivalTime":"07:45:00","departureTime":"05:30:00"},{"airlineIata":"RJ","arrivalIata":"BGW","departureIata":"AMM","codeshares":null,"flightNumber":"5810","arrivalTime":"08:00:00","departureTime":"05:30:00"},{"airlineIata":"RJ","arrivalIata":"AYT","departureIata":"AMM","codeshares":null,"flightNumber":"6007","arrivalTime":null,"departureTime":null},{"airlineIata":"RJ","arrivalIata":"AYT","departureIata":"AMM","codeshares":null,"flightNumber":"6050","arrivalTime":null,"departureTime":null},{"airlineIata":"RJ","arrivalIata":"AYT","departureIata":"AMM","codeshares":null,"flightNumber":"6056","arrivalTime":null,"departureTime":null},{"airlineIata":"RJ","arrivalIata":"BJV","departureIata":"AMM","codeshares":null,"flightNumber":"6064","arrivalTime":null,"departureTime":null},{"airlineIata":"RJ","arrivalIata":"BGW","departureIata":"AMM","codeshares":null,"flightNumber":"61","arrivalTime":null,"departureTime":null},{"airlineIata":"RJ","arrivalIata":"DXB","departureIata":"AMM","codeshares":null,"flightNumber":"610","arrivalTime":"12:00:00","departureTime":"08:00:00"},{"airlineIata":"RJ","arrivalIata":"BEY","departureIata":"AMM","codeshares":null,"flightNumber":"6100","arrivalTime":null,"departureTime":null},{"airlineIata":"RJ","arrivalIata":"TLV","departureIata":"AMM","codeshares":null,"flightNumber":"6102","arrivalTime":null,"departureTime":null},{"airlineIata":"RJ","arrivalIata":"TLV","departureIata":"AMM","codeshares":null,"flightNumber":"6104","arrivalTime":null,"departureTime":null},{"airlineIata":"RJ","arrivalIata":"TLV","departureIata":"AMM","codeshares":null,"flightNumber":"6116","arrivalTime":null,"departureTime":null},{"airlineIata":"RJ","arrivalIata":"DXB","departureIata":"AMM","codeshares":null,"flightNumber":"612","arrivalTime":"00:30:00","departureTime":"20:30:00"},{"airlineIata":"RJ","arrivalIata":"TLV","departureIata":"AMM","codeshares":null,"flightNumber":"6122","arrivalTime":null,"departureTime":null},{"airlineIata":"RJ","arrivalIata":"TLV","departureIata":"AMM","codeshares":null,"flightNumber":"6126","arrivalTime":null,"departureTime":null},{"airlineIata":"RJ","arrivalIata":"DXB","departureIata":"AMM","codeshares":null,"flightNumber":"614","arrivalTime":"20:30:00","departureTime":"16:30:00"},{"airlineIata":"RJ","arrivalIata":"TLV","departureIata":"AMM","codeshares":null,"flightNumber":"6140","arrivalTime":null,"departureTime":null},{"airlineIata":"RJ","arrivalIata":"TLV","departureIata":"AMM","codeshares":null,"flightNumber":"6150","arrivalTime":null,"departureTime":null},{"airlineIata":"RJ","arrivalIata":"TLV","departureIata":"AMM","codeshares":null,"flightNumber":"6152","arrivalTime":null,"departureTime":null},{"airlineIata":"RJ","arrivalIata":"TLV","departureIata":"AMM","codeshares":null,"flightNumber":"6154","arrivalTime":null,"departureTime":null},{"airlineIata":"RJ","arrivalIata":"TLV","departureIata":"AMM","codeshares":null,"flightNumber":"6158","arrivalTime":null,"departureTime":null},{"airlineIata":"RJ","arrivalIata":"TLV","departureIata":"AMM","codeshares":null,"flightNumber":"6164","arrivalTime":null,"departureTime":null},{"airlineIata":"RJ","arrivalIata":"TLV","departureIata":"AMM","codeshares":null,"flightNumber":"6184","arrivalTime":null,"departureTime":null},{"airlineIata":"RJ","arrivalIata":"AUH","departureIata":"AMM","codeshares":null,"flightNumber":"620","arrivalTime":"16:10:00","departureTime":"12:00:00"},{"airlineIata":"RJ","arrivalIata":"TLV","departureIata":"AMM","codeshares":null,"flightNumber":"6200","arrivalTime":null,"departureTime":null},{"airlineIata":"RJ","arrivalIata":"AYT","departureIata":"AMM","codeshares":null,"flightNumber":"6202","arrivalTime":null,"departureTime":null},{"airlineIata":"RJ","arrivalIata":"TLV","departureIata":"AMM","codeshares":null,"flightNumber":"6204","arrivalTime":null,"departureTime":null},{"airlineIata":"RJ","arrivalIata":"TLV","departureIata":"AMM","codeshares":null,"flightNumber":"6206","arrivalTime":null,"departureTime":null},{"airlineIata":"RJ","arrivalIata":"TLV","departureIata":"AMM","codeshares":null,"flightNumber":"6208","arrivalTime":null,"departureTime":null},{"airlineIata":"RJ","arrivalIata":"TLV","departureIata":"AMM","codeshares":null,"flightNumber":"6214","arrivalTime":null,"departureTime":null},{"airlineIata":"RJ","arrivalIata":"TLV","departureIata":"AMM","codeshares":null,"flightNumber":"6216","arrivalTime":null,"departureTime":null},{"airlineIata":"RJ","arrivalIata":"AUH","departureIata":"AMM","codeshares":null,"flightNumber":"622","arrivalTime":"00:40:00","departureTime":"20:30:00"},{"airlineIata":"RJ","arrivalIata":"TLV","departureIata":"AMM","codeshares":null,"flightNumber":"6220","arrivalTime":null,"departureTime":null},{"airlineIata":"RJ","arrivalIata":"TLV","departureIata":"AMM","codeshares":null,"flightNumber":"6222","arrivalTime":null,"departureTime":null},{"airlineIata":"RJ","arrivalIata":"TLV","departureIata":"AMM","codeshares":null,"flightNumber":"6224","arrivalTime":null,"departureTime":null},{"airlineIata":"RJ","arrivalIata":"TLV","departureIata":"AMM","codeshares":null,"flightNumber":"6240","arrivalTime":null,"departureTime":null},{"airlineIata":"RJ","arrivalIata":"HRG","departureIata":"AMM","codeshares":null,"flightNumber":"6333","arrivalTime":null,"departureTime":null},{"airlineIata":"RJ","arrivalIata":"AYT","departureIata":"AMM","codeshares":null,"flightNumber":"6342","arrivalTime":null,"departureTime":null},{"airlineIata":"RJ","arrivalIata":"KWI","departureIata":"AMM","codeshares":null,"flightNumber":"640","arrivalTime":"16:00:00","departureTime":"13:55:00"},{"airlineIata":"RJ","arrivalIata":"KWI","departureIata":"AMM","codeshares":[{"airline_code":"AA","flight_number":"7181"}],"flightNumber":"642","arrivalTime":"00:15:00","departureTime":"22:10:00"},{"airlineIata":"RJ","arrivalIata":"AYT","departureIata":"AMM","codeshares":null,"flightNumber":"6428","arrivalTime":null,"departureTime":null},{"airlineIata":"RJ","arrivalIata":"KWI","departureIata":"AMM","codeshares":null,"flightNumber":"644","arrivalTime":"03:10:00","departureTime":"01:05:00"},{"airlineIata":"RJ","arrivalIata":"DOH","departureIata":"AMM","codeshares":[{"airline_code":"QR","flight_number":"6103"}],"flightNumber":"646","arrivalTime":"11:30:00","departureTime":"09:00:00"},{"airlineIata":"RJ","arrivalIata":"KWI","departureIata":"AMM","codeshares":null,"flightNumber":"648","arrivalTime":"09:30:00","departureTime":"07:25:00"},{"airlineIata":"RJ","arrivalIata":"DOH","departureIata":"AMM","codeshares":[{"airline_code":"QR","flight_number":"6101"}],"flightNumber":"650","arrivalTime":"05:20:00","departureTime":"02:50:00"},{"airlineIata":"RJ","arrivalIata":"SAW","departureIata":"AMM","codeshares":null,"flightNumber":"6500","arrivalTime":null,"departureTime":null},{"airlineIata":"RJ","arrivalIata":"AYT","departureIata":"AMM","codeshares":null,"flightNumber":"6504","arrivalTime":null,"departureTime":null},{"airlineIata":"RJ","arrivalIata":"SAW","departureIata":"AMM","codeshares":null,"flightNumber":"6555","arrivalTime":null,"departureTime":null},{"airlineIata":"RJ","arrivalIata":"AYT","departureIata":"AMM","codeshares":null,"flightNumber":"6557","arrivalTime":null,"departureTime":null},{"airlineIata":"RJ","arrivalIata":"BUS","departureIata":"AMM","codeshares":null,"flightNumber":"6618","arrivalTime":null,"departureTime":null},{"airlineIata":"RJ","arrivalIata":"AYT","departureIata":"AMM","codeshares":null,"flightNumber":"6640","arrivalTime":null,"departureTime":null},{"airlineIata":"RJ","arrivalIata":"AYT","departureIata":"AMM","codeshares":null,"flightNumber":"6717","arrivalTime":null,"departureTime":null},{"airlineIata":"RJ","arrivalIata":"AYT","departureIata":"AMM","codeshares":null,"flightNumber":"6718","arrivalTime":null,"departureTime":null},{"airlineIata":"RJ","arrivalIata":"DLM","departureIata":"AMM","codeshares":null,"flightNumber":"6770","arrivalTime":null,"departureTime":null},{"airlineIata":"RJ","arrivalIata":"AYT","departureIata":"AMM","codeshares":null,"flightNumber":"6772","arrivalTime":null,"departureTime":null},{"airlineIata":"RJ","arrivalIata":"BFS","departureIata":"AMM","codeshares":null,"flightNumber":"6775","arrivalTime":null,"departureTime":null},{"airlineIata":"RJ","arrivalIata":"AYT","departureIata":"AMM","codeshares":null,"flightNumber":"6778","arrivalTime":null,"departureTime":null},{"airlineIata":"RJ","arrivalIata":"AYT","departureIata":"AMM","codeshares":null,"flightNumber":"6780","arrivalTime":null,"departureTime":null},{"airlineIata":"RJ","arrivalIata":"AYT","departureIata":"AMM","codeshares":null,"flightNumber":"6900","arrivalTime":null,"departureTime":null},{"airlineIata":"RJ","arrivalIata":"SAW","departureIata":"AMM","codeshares":null,"flightNumber":"6902","arrivalTime":null,"departureTime":null},{"airlineIata":"RJ","arrivalIata":"AYT","departureIata":"AMM","codeshares":null,"flightNumber":"6906","arrivalTime":null,"departureTime":null},{"airlineIata":"RJ","arrivalIata":"AYT","departureIata":"AMM","codeshares":null,"flightNumber":"6908","arrivalTime":null,"departureTime":null},{"airlineIata":"RJ","arrivalIata":"DLM","departureIata":"AMM","codeshares":null,"flightNumber":"6910","arrivalTime":null,"departureTime":null},{"airlineIata":"RJ","arrivalIata":"BUS","departureIata":"AMM","codeshares":null,"flightNumber":"6922","arrivalTime":null,"departureTime":null},{"airlineIata":"RJ","arrivalIata":"JED","departureIata":"AMM","codeshares":null,"flightNumber":"700","arrivalTime":"22:25:00","departureTime":"20:15:00"},{"airlineIata":"RJ","arrivalIata":"JED","departureIata":"AMM","codeshares":null,"flightNumber":"702","arrivalTime":"13:55:00","departureTime":"11:45:00"},{"airlineIata":"RJ","arrivalIata":"JED","departureIata":"AMM","codeshares":null,"flightNumber":"704","arrivalTime":"04:55:00","departureTime":"02:45:00"},{"airlineIata":"RJ","arrivalIata":"JED","departureIata":"AMM","codeshares":null,"flightNumber":"708","arrivalTime":"08:10:00","departureTime":"06:00:00"},{"airlineIata":"RJ","arrivalIata":"DOH","departureIata":"AMM","codeshares":null,"flightNumber":"71","arrivalTime":null,"departureTime":null},{"airlineIata":"RJ","arrivalIata":"MED","departureIata":"AMM","codeshares":null,"flightNumber":"720","arrivalTime":"22:15:00","departureTime":"20:30:00"},{"airlineIata":"RJ","arrivalIata":"MED","departureIata":"AMM","codeshares":null,"flightNumber":"722","arrivalTime":"04:30:00","departureTime":"02:45:00"},{"airlineIata":"RJ","arrivalIata":"MED","departureIata":"AMM","codeshares":null,"flightNumber":"728","arrivalTime":"07:45:00","departureTime":"06:00:00"},{"airlineIata":"RJ","arrivalIata":"RUH","departureIata":"AMM","codeshares":null,"flightNumber":"730","arrivalTime":"18:00:00","departureTime":"15:50:00"},{"airlineIata":"RJ","arrivalIata":"RUH","departureIata":"AMM","codeshares":null,"flightNumber":"732","arrivalTime":"11:25:00","departureTime":"09:15:00"},{"airlineIata":"RJ","arrivalIata":"RUH","departureIata":"AMM","codeshares":null,"flightNumber":"734","arrivalTime":"00:40:00","departureTime":"22:30:00"},{"airlineIata":"RJ","arrivalIata":"DMM","departureIata":"AMM","codeshares":null,"flightNumber":"740","arrivalTime":"19:45:00","departureTime":"17:30:00"},{"airlineIata":"RJ","arrivalIata":"DMM","departureIata":"AMM","codeshares":null,"flightNumber":"742","arrivalTime":"23:00:00","departureTime":"20:45:00"},{"airlineIata":"RJ","arrivalIata":"DMM","departureIata":"AMM","codeshares":null,"flightNumber":"744","arrivalTime":"03:15:00","departureTime":"00:05:00"},{"airlineIata":"RJ","arrivalIata":"TUU","departureIata":"AMM","codeshares":null,"flightNumber":"750","arrivalTime":"19:30:00","departureTime":"18:30:00"},{"airlineIata":"RJ","arrivalIata":"ISU","departureIata":"AMM","codeshares":null,"flightNumber":"800","arrivalTime":"04:15:00","departureTime":"02:15:00"},{"airlineIata":"RJ","arrivalIata":"BGW","departureIata":"AMM","codeshares":null,"flightNumber":"810","arrivalTime":"08:00:00","departureTime":"06:30:00"},{"airlineIata":"RJ","arrivalIata":"BGW","departureIata":"AMM","codeshares":null,"flightNumber":"812","arrivalTime":"17:30:00","departureTime":"16:00:00"},{"airlineIata":"RJ","arrivalIata":"BGW","departureIata":"AMM","codeshares":null,"flightNumber":"814","arrivalTime":"07:30:00","departureTime":"06:00:00"},{"airlineIata":"RJ","arrivalIata":"EBL","departureIata":"AMM","codeshares":null,"flightNumber":"820","arrivalTime":"12:30:00","departureTime":"10:30:00"},{"airlineIata":"RJ","arrivalIata":"EBL","departureIata":"AMM","codeshares":null,"flightNumber":"822","arrivalTime":"03:30:00","departureTime":"01:30:00"},{"airlineIata":"RJ","arrivalIata":"EBL","departureIata":"AMM","codeshares":null,"flightNumber":"824","arrivalTime":"05:30:00","departureTime":"03:45:00"},{"airlineIata":"RJ","arrivalIata":"BSR","departureIata":"AMM","codeshares":null,"flightNumber":"830","arrivalTime":"08:00:00","departureTime":"06:00:00"},{"airlineIata":"RJ","arrivalIata":"NJF","departureIata":"AMM","codeshares":null,"flightNumber":"840","arrivalTime":"03:50:00","departureTime":"02:15:00"},{"airlineIata":"RJ","arrivalIata":"CAI","departureIata":"AMM","codeshares":null,"flightNumber":"8507","arrivalTime":"00:35:00","departureTime":"00:05:00"},{"airlineIata":"RJ","arrivalIata":"DXB","departureIata":"AMM","codeshares":null,"flightNumber":"8612","arrivalTime":"04:45:00","departureTime":"00:45:00"},{"airlineIata":"RJ","arrivalIata":"AUH","departureIata":"AMM","codeshares":null,"flightNumber":"8622","arrivalTime":"06:30:00","departureTime":"02:20:00"},{"airlineIata":"RJ","arrivalIata":"KWI","departureIata":"AMM","codeshares":null,"flightNumber":"8642","arrivalTime":"03:25:00","departureTime":"01:20:00"},{"airlineIata":"RO","arrivalIata":"OTP","departureIata":"AMM","codeshares":[{"airline_code":"RJ","flight_number":"3358"}],"flightNumber":"188","arrivalTime":"05:35:00","departureTime":"02:50:00"},{"airlineIata":"SV","arrivalIata":"JED","departureIata":"AMM","codeshares":null,"flightNumber":"630","arrivalTime":"16:05:00","departureTime":"14:00:00"},{"airlineIata":"SV","arrivalIata":"JED","departureIata":"AMM","codeshares":null,"flightNumber":"632","arrivalTime":"16:05:00","departureTime":"14:00:00"},{"airlineIata":"SV","arrivalIata":"RUH","departureIata":"AMM","codeshares":null,"flightNumber":"634","arrivalTime":"18:10:00","departureTime":"16:00:00"},{"airlineIata":"SV","arrivalIata":"JED","departureIata":"AMM","codeshares":null,"flightNumber":"636","arrivalTime":"01:20:00","departureTime":"22:15:00"},{"airlineIata":"SV","arrivalIata":"RUH","departureIata":"AMM","codeshares":null,"flightNumber":"638","arrivalTime":"23:10:00","departureTime":"21:00:00"},{"airlineIata":"SV","arrivalIata":"JED","departureIata":"AMM","codeshares":null,"flightNumber":"696","arrivalTime":"01:20:00","departureTime":"23:15:00"},{"airlineIata":"MT","arrivalIata":"MAN","departureIata":"AMM","codeshares":null,"flightNumber":"4986","arrivalTime":null,"departureTime":null},{"airlineIata":"TK","arrivalIata":"AYT","departureIata":"AMM","codeshares":null,"flightNumber":"1181","arrivalTime":"05:40:00","departureTime":"04:00:00"},{"airlineIata":"TK","arrivalIata":"IST","departureIata":"AMM","codeshares":null,"flightNumber":"3923","arrivalTime":null,"departureTime":null},{"airlineIata":"TK","arrivalIata":"IST","departureIata":"AMM","codeshares":[{"airline_code":"AC","flight_number":"6683"},{"airline_code":"AT","flight_number":"9427"},{"airline_code":"LO","flight_number":"4610"},{"airline_code":"RJ","flight_number":"3701"}],"flightNumber":"813","arrivalTime":"09:05:00","departureTime":"06:40:00"},{"airlineIata":"TK","arrivalIata":"IST","departureIata":"AMM","codeshares":[{"airline_code":"RJ","flight_number":"3703"}],"flightNumber":"815","arrivalTime":"04:45:00","departureTime":"02:20:00"},{"airlineIata":"TK","arrivalIata":"IST","departureIata":"AMM","codeshares":null,"flightNumber":"817","arrivalTime":"05:30:00","departureTime":"02:05:00"},{"airlineIata":"WY","arrivalIata":"MCT","departureIata":"AMM","codeshares":[{"airline_code":"RJ","flight_number":"3202"}],"flightNumber":"412","arrivalTime":"06:55:00","departureTime":"02:20:00"},{"airlineIata":"WY","arrivalIata":"MCT","departureIata":"AMM","codeshares":[{"airline_code":"RJ","flight_number":"3204"}],"flightNumber":"414","arrivalTime":"00:20:00","departureTime":"19:50:00"},{"airlineIata":"WY","arrivalIata":"MCT","departureIata":"AMM","codeshares":null,"flightNumber":"4412","arrivalTime":"06:50:00","departureTime":"01:35:00"},{"airlineIata":"XY","arrivalIata":"RUH","departureIata":"AMM","codeshares":null,"flightNumber":"252","arrivalTime":"17:50:00","departureTime":"15:40:00"},{"airlineIata":"XY","arrivalIata":"RUH","departureIata":"AMM","codeshares":null,"flightNumber":"254","arrivalTime":"00:50:00","departureTime":"22:40:00"},{"airlineIata":"XY","arrivalIata":"JED","departureIata":"AMM","codeshares":null,"flightNumber":"552","arrivalTime":"18:00:00","departureTime":"15:40:00"},{"airlineIata":"XY","arrivalIata":"JED","departureIata":"AMM","codeshares":null,"flightNumber":"554","arrivalTime":"18:20:00","departureTime":"16:00:00"},{"airlineIata":"XY","arrivalIata":"MED","departureIata":"AMM","codeshares":null,"flightNumber":"688","arrivalTime":"11:45:00","departureTime":"10:05:00"},{"airlineIata":"D8","arrivalIata":"CPH","departureIata":"AMM","codeshares":null,"flightNumber":"3779","arrivalTime":"03:35:00","departureTime":"23:35:00"},{"airlineIata":"E5","arrivalIata":"HBE","departureIata":"AMM","codeshares":null,"flightNumber":"524","arrivalTime":"01:50:00","departureTime":"01:10:00"}]