[{"airlineIata":"8Q","arrivalIata":"IST","departureIata":"GNY","codeshares":null,"flightNumber":"79","arrivalTime":"10:00:00","departureTime":"08:15:00"},{"airlineIata":"PC","arrivalIata":"ADB","departureIata":"GNY","codeshares":null,"flightNumber":"2257","arrivalTime":"13:30:00","departureTime":"11:35:00"},{"airlineIata":"PC","arrivalIata":"SAW","departureIata":"GNY","codeshares":null,"flightNumber":"257","arrivalTime":"10:35:00","departureTime":"08:45:00"},{"airlineIata":"PC","arrivalIata":"ADB","departureIata":"GNY","codeshares":null,"flightNumber":"3051","arrivalTime":"10:50:00","departureTime":"08:50:00"},{"airlineIata":"PC","arrivalIata":"SAW","departureIata":"GNY","codeshares":null,"flightNumber":"4257","arrivalTime":"11:25:00","departureTime":"09:35:00"},{"airlineIata":"PC","arrivalIata":"ADB","departureIata":"GNY","codeshares":null,"flightNumber":"4507","arrivalTime":"01:45:00","departureTime":"23:45:00"},{"airlineIata":"PC","arrivalIata":"ADB","departureIata":"GNY","codeshares":null,"flightNumber":"4621","arrivalTime":"14:45:00","departureTime":"12:45:00"},{"airlineIata":"PC","arrivalIata":"ADB","departureIata":"GNY","codeshares":null,"flightNumber":"4677","arrivalTime":"01:15:00","departureTime":"23:15:00"},{"airlineIata":"PC","arrivalIata":"SAW","departureIata":"GNY","codeshares":null,"flightNumber":"4863","arrivalTime":"06:45:00","departureTime":"04:55:00"},{"airlineIata":"PC","arrivalIata":"ESB","departureIata":"GNY","codeshares":null,"flightNumber":"8301","arrivalTime":"10:30:00","departureTime":"09:10:00"},{"airlineIata":"TK","arrivalIata":"IST","departureIata":"GNY","codeshares":null,"flightNumber":"2247","arrivalTime":"09:50:00","departureTime":"07:50:00"},{"airlineIata":"TK","arrivalIata":"IST","departureIata":"GNY","codeshares":null,"flightNumber":"2249","arrivalTime":"00:30:00","departureTime":"22:30:00"},{"airlineIata":"TK","arrivalIata":"ESB","departureIata":"GNY","codeshares":null,"flightNumber":"7115","arrivalTime":"11:25:00","departureTime":"10:05:00"},{"airlineIata":"TK","arrivalIata":"ESB","departureIata":"GNY","codeshares":null,"flightNumber":"7117","arrivalTime":"07:30:00","departureTime":"06:10:00"},{"airlineIata":"TK","arrivalIata":"ESB","departureIata":"GNY","codeshares":null,"flightNumber":"7119","arrivalTime":"07:20:00","departureTime":"06:00:00"},{"airlineIata":"TK","arrivalIata":"SAW","departureIata":"GNY","codeshares":null,"flightNumber":"7317","arrivalTime":"15:25:00","departureTime":"13:35:00"},{"airlineIata":"XQ","arrivalIata":"ESB","departureIata":"GNY","codeshares":[{"airline_code":"TK","flight_number":"7115"}],"flightNumber":"7115","arrivalTime":"11:30:00","departureTime":"10:10:00"},{"airlineIata":"XQ","arrivalIata":"ESB","departureIata":"GNY","codeshares":[{"airline_code":"TK","flight_number":"7117"}],"flightNumber":"7117","arrivalTime":"07:50:00","departureTime":"06:30:00"},{"airlineIata":"XQ","arrivalIata":"ESB","departureIata":"GNY","codeshares":[{"airline_code":"TK","flight_number":"7119"}],"flightNumber":"7119","arrivalTime":"07:20:00","departureTime":"06:00:00"},{"airlineIata":"XQ","arrivalIata":"SAW","departureIata":"GNY","codeshares":[{"airline_code":"TK","flight_number":"7317"}],"flightNumber":"7317","arrivalTime":"15:25:00","departureTime":"13:35:00"},{"airlineIata":"XQ","arrivalIata":"HAJ","departureIata":"GNY","codeshares":null,"flightNumber":"772","arrivalTime":"09:15:00","departureTime":"05:55:00"}]