[{"airlineIata":"3E","arrivalIata":"STL","departureIata":"JBR","codeshares":null,"flightNumber":"2700","arrivalTime":"08:00:00","departureTime":"06:30:00"},{"airlineIata":"3E","arrivalIata":"STL","departureIata":"JBR","codeshares":null,"flightNumber":"2706","arrivalTime":"10:00:00","departureTime":"08:30:00"},{"airlineIata":"3E","arrivalIata":"STL","departureIata":"JBR","codeshares":null,"flightNumber":"2708","arrivalTime":"14:30:00","departureTime":"13:00:00"},{"airlineIata":"3E","arrivalIata":"STL","departureIata":"JBR","codeshares":null,"flightNumber":"2710","arrivalTime":"18:30:00","departureTime":"17:00:00"}]