[{"airlineIata":"6I","arrivalIata":"KEF","departureIata":"KOA","codeshares":null,"flightNumber":"622","arrivalTime":null,"departureTime":null},{"airlineIata":"AA","arrivalIata":"DFW","departureIata":"KOA","codeshares":null,"flightNumber":"230","arrivalTime":"05:59:00","departureTime":"18:40:00"},{"airlineIata":"AA","arrivalIata":"LAX","departureIata":"KOA","codeshares":[{"airline_code":"AS","flight_number":"1846"},{"airline_code":"BA","flight_number":"4977"}],"flightNumber":"246","arrivalTime":"06:19:00","departureTime":"22:00:00"},{"airlineIata":"AA","arrivalIata":"LAX","departureIata":"KOA","codeshares":[{"airline_code":"AS","flight_number":"1161"},{"airline_code":"BA","flight_number":"8409"}],"flightNumber":"58","arrivalTime":"23:20:00","departureTime":"15:04:00"},{"airlineIata":"AA","arrivalIata":"PHX","departureIata":"KOA","codeshares":null,"flightNumber":"664","arrivalTime":"07:32:00","departureTime":"22:50:00"},{"airlineIata":"AS","arrivalIata":"PDX","departureIata":"KOA","codeshares":null,"flightNumber":"802","arrivalTime":"19:15:00","departureTime":"11:40:00"},{"airlineIata":"AS","arrivalIata":"SAN","departureIata":"KOA","codeshares":null,"flightNumber":"804","arrivalTime":"21:18:00","departureTime":"12:35:00"},{"airlineIata":"AS","arrivalIata":"OAK","departureIata":"KOA","codeshares":null,"flightNumber":"826","arrivalTime":"23:23:00","departureTime":"15:20:00"},{"airlineIata":"AS","arrivalIata":"SEA","departureIata":"KOA","codeshares":[{"airline_code":"EK","flight_number":"3042"}],"flightNumber":"850","arrivalTime":"07:13:00","departureTime":"22:20:00"},{"airlineIata":"AS","arrivalIata":"SJC","departureIata":"KOA","codeshares":null,"flightNumber":"856","arrivalTime":"20:57:00","departureTime":"13:00:00"},{"airlineIata":"AS","arrivalIata":"SEA","departureIata":"KOA","codeshares":null,"flightNumber":"876","arrivalTime":"19:45:00","departureTime":"11:00:00"},{"airlineIata":"AS","arrivalIata":"SEA","departureIata":"KOA","codeshares":null,"flightNumber":"880","arrivalTime":"07:00:00","departureTime":"23:05:00"},{"airlineIata":"DL","arrivalIata":"SEA","departureIata":"KOA","codeshares":[{"airline_code":"VS","flight_number":"3409"}],"flightNumber":"1055","arrivalTime":"07:06:00","departureTime":"22:10:00"},{"airlineIata":"DL","arrivalIata":"LAX","departureIata":"KOA","codeshares":[{"airline_code":"AF","flight_number":"8973"},{"airline_code":"AM","flight_number":"5272"},{"airline_code":"AZ","flight_number":"5287"},{"airline_code":"KL","flight_number":"5619"},{"airline_code":"MU","flight_number":"4318"},{"airline_code":"VS","flight_number":"4064"}],"flightNumber":"2116","arrivalTime":"05:10:00","departureTime":"20:58:00"},{"airlineIata":"DL","arrivalIata":"SEA","departureIata":"KOA","codeshares":[{"airline_code":"VS","flight_number":"3409"}],"flightNumber":"584","arrivalTime":"06:25:00","departureTime":"21:38:00"},{"airlineIata":"DL","arrivalIata":"LAX","departureIata":"KOA","codeshares":null,"flightNumber":"9857","arrivalTime":null,"departureTime":null},{"airlineIata":"EM","arrivalIata":"OGG","departureIata":"KOA","codeshares":[{"airline_code":"HA","flight_number":"641"}],"flightNumber":"641","arrivalTime":"09:37:00","departureTime":"09:00:00"},{"airlineIata":"EM","arrivalIata":"OGG","departureIata":"KOA","codeshares":[{"airline_code":"HA","flight_number":"645"}],"flightNumber":"645","arrivalTime":"17:42:00","departureTime":"17:05:00"},{"airlineIata":"HA","arrivalIata":"HNL","departureIata":"KOA","codeshares":[{"airline_code":"DL","flight_number":"6824"},{"airline_code":"KE","flight_number":"7816"}],"flightNumber":"107","arrivalTime":"06:57:00","departureTime":"06:15:00"},{"airlineIata":"HA","arrivalIata":"HNL","departureIata":"KOA","codeshares":[{"airline_code":"AA","flight_number":"7869"}],"flightNumber":"1107","arrivalTime":"11:32:00","departureTime":"10:47:00"},{"airlineIata":"HA","arrivalIata":"HNL","departureIata":"KOA","codeshares":null,"flightNumber":"1117","arrivalTime":"07:45:00","departureTime":"07:03:00"},{"airlineIata":"HA","arrivalIata":"HNL","departureIata":"KOA","codeshares":null,"flightNumber":"1127","arrivalTime":"08:52:00","departureTime":"08:09:00"},{"airlineIata":"HA","arrivalIata":"HNL","departureIata":"KOA","codeshares":null,"flightNumber":"1137","arrivalTime":"09:17:00","departureTime":"08:34:00"},{"airlineIata":"HA","arrivalIata":"HNL","departureIata":"KOA","codeshares":null,"flightNumber":"1157","arrivalTime":"11:27:00","departureTime":"10:40:00"},{"airlineIata":"HA","arrivalIata":"HNL","departureIata":"KOA","codeshares":null,"flightNumber":"1167","arrivalTime":"07:56:00","departureTime":"07:10:00"},{"airlineIata":"HA","arrivalIata":"HNL","departureIata":"KOA","codeshares":[{"airline_code":"DL","flight_number":"6855"},{"airline_code":"KE","flight_number":"7818"},{"airline_code":"NH","flight_number":"5613"},{"airline_code":"PR","flight_number":"1015"}],"flightNumber":"117","arrivalTime":"09:04:00","departureTime":"08:21:00"},{"airlineIata":"HA","arrivalIata":"HNL","departureIata":"KOA","codeshares":[{"airline_code":"AA","flight_number":"7885"},{"airline_code":"KE","flight_number":"7820"},{"airline_code":"NH","flight_number":"5615"},{"airline_code":"UA","flight_number":"7862"},{"airline_code":"VA","flight_number":"5109"}],"flightNumber":"119","arrivalTime":"11:12:00","departureTime":"10:28:00"},{"airlineIata":"HA","arrivalIata":"HNL","departureIata":"KOA","codeshares":[{"airline_code":"B6","flight_number":"5861"},{"airline_code":"DL","flight_number":"6823"}],"flightNumber":"127","arrivalTime":"14:26:00","departureTime":"13:39:00"},{"airlineIata":"HA","arrivalIata":"HNL","departureIata":"KOA","codeshares":[{"airline_code":"B6","flight_number":"5863"},{"airline_code":"DL","flight_number":"6860"}],"flightNumber":"137","arrivalTime":"14:41:00","departureTime":"13:54:00"},{"airlineIata":"HA","arrivalIata":"OGG","departureIata":"KOA","codeshares":null,"flightNumber":"139","arrivalTime":"13:15:00","departureTime":"12:40:00"},{"airlineIata":"HA","arrivalIata":"HNL","departureIata":"KOA","codeshares":[{"airline_code":"AA","flight_number":"7888"},{"airline_code":"NH","flight_number":"5623"},{"airline_code":"UA","flight_number":"7837"}],"flightNumber":"147","arrivalTime":"16:02:00","departureTime":"15:15:00"},{"airlineIata":"HA","arrivalIata":"HNL","departureIata":"KOA","codeshares":[{"airline_code":"DL","flight_number":"6807"}],"flightNumber":"167","arrivalTime":"11:41:00","departureTime":"10:56:00"},{"airlineIata":"HA","arrivalIata":"HNL","departureIata":"KOA","codeshares":[{"airline_code":"AA","flight_number":"7909"},{"airline_code":"DL","flight_number":"6810"}],"flightNumber":"177","arrivalTime":"13:04:00","departureTime":"12:17:00"},{"airlineIata":"HA","arrivalIata":"HNL","departureIata":"KOA","codeshares":[{"airline_code":"AA","flight_number":"7907"},{"airline_code":"UA","flight_number":"7797"}],"flightNumber":"187","arrivalTime":"20:12:00","departureTime":"19:27:00"},{"airlineIata":"HA","arrivalIata":"HNL","departureIata":"KOA","codeshares":[{"airline_code":"DL","flight_number":"6822"},{"airline_code":"NH","flight_number":"5627"}],"flightNumber":"189","arrivalTime":"16:50:00","departureTime":"16:05:00"},{"airlineIata":"HA","arrivalIata":"HNL","departureIata":"KOA","codeshares":[{"airline_code":"AA","flight_number":"7907"},{"airline_code":"DL","flight_number":"6820"},{"airline_code":"KE","flight_number":"7824"},{"airline_code":"NH","flight_number":"5619"},{"airline_code":"UA","flight_number":"7793"}],"flightNumber":"207","arrivalTime":"11:36:00","departureTime":"10:52:00"},{"airlineIata":"HA","arrivalIata":"HNL","departureIata":"KOA","codeshares":[{"airline_code":"DL","flight_number":"6816"},{"airline_code":"NH","flight_number":"5611"}],"flightNumber":"217","arrivalTime":"07:45:00","departureTime":"07:03:00"},{"airlineIata":"HA","arrivalIata":"HNL","departureIata":"KOA","codeshares":[{"airline_code":"CI","flight_number":"9187"},{"airline_code":"DL","flight_number":"6848"},{"airline_code":"KE","flight_number":"7826"},{"airline_code":"NH","flight_number":"5617"},{"airline_code":"UA","flight_number":"7878"}],"flightNumber":"227","arrivalTime":"12:06:00","departureTime":"11:19:00"},{"airlineIata":"HA","arrivalIata":"OGG","departureIata":"KOA","codeshares":[{"airline_code":"DL","flight_number":"6847"}],"flightNumber":"229","arrivalTime":"12:27:00","departureTime":"11:52:00"},{"airlineIata":"HA","arrivalIata":"HNL","departureIata":"KOA","codeshares":[{"airline_code":"AA","flight_number":"7895"},{"airline_code":"KE","flight_number":"7834"},{"airline_code":"UA","flight_number":"7815"}],"flightNumber":"247","arrivalTime":"20:02:00","departureTime":"19:17:00"},{"airlineIata":"HA","arrivalIata":"HNL","departureIata":"KOA","codeshares":[{"airline_code":"AA","flight_number":"7936"},{"airline_code":"B6","flight_number":"5875"},{"airline_code":"CA","flight_number":"6986"},{"airline_code":"NH","flight_number":"5625"}],"flightNumber":"257","arrivalTime":"15:18:00","departureTime":"14:31:00"},{"airlineIata":"HA","arrivalIata":"HNL","departureIata":"KOA","codeshares":[{"airline_code":"B6","flight_number":"5877"},{"airline_code":"DL","flight_number":"6859"},{"airline_code":"NH","flight_number":"5621"}],"flightNumber":"267","arrivalTime":"13:02:00","departureTime":"12:15:00"},{"airlineIata":"HA","arrivalIata":"OGG","departureIata":"KOA","codeshares":null,"flightNumber":"269","arrivalTime":"13:30:00","departureTime":"12:55:00"},{"airlineIata":"HA","arrivalIata":"HNL","departureIata":"KOA","codeshares":[{"airline_code":"AA","flight_number":"7901"}],"flightNumber":"277","arrivalTime":"19:22:00","departureTime":"18:37:00"},{"airlineIata":"HA","arrivalIata":"HNL","departureIata":"KOA","codeshares":[{"airline_code":"AA","flight_number":"7917"},{"airline_code":"CA","flight_number":"6988"},{"airline_code":"DL","flight_number":"6816"},{"airline_code":"UA","flight_number":"7848"}],"flightNumber":"279","arrivalTime":"18:21:00","departureTime":"17:36:00"},{"airlineIata":"HA","arrivalIata":"HNL","departureIata":"KOA","codeshares":[{"airline_code":"DL","flight_number":"6832"},{"airline_code":"NH","flight_number":"7879"}],"flightNumber":"287","arrivalTime":"16:26:00","departureTime":"15:39:00"},{"airlineIata":"HA","arrivalIata":"HNL","departureIata":"KOA","codeshares":[{"airline_code":"NH","flight_number":"7875"},{"airline_code":"UA","flight_number":"7866"}],"flightNumber":"297","arrivalTime":"17:16:00","departureTime":"16:31:00"},{"airlineIata":"HA","arrivalIata":"OGG","departureIata":"KOA","codeshares":null,"flightNumber":"299","arrivalTime":"14:00:00","departureTime":"13:26:00"},{"airlineIata":"HA","arrivalIata":"HNL","departureIata":"KOA","codeshares":[{"airline_code":"DL","flight_number":"6856"},{"airline_code":"KE","flight_number":"7836"},{"airline_code":"UA","flight_number":"7821"}],"flightNumber":"307","arrivalTime":"20:54:00","departureTime":"20:09:00"},{"airlineIata":"HA","arrivalIata":"HNL","departureIata":"KOA","codeshares":[{"airline_code":"B6","flight_number":"5882"}],"flightNumber":"317","arrivalTime":"13:45:00","departureTime":"12:58:00"},{"airlineIata":"HA","arrivalIata":"HNL","departureIata":"KOA","codeshares":[{"airline_code":"AA","flight_number":"7861"},{"airline_code":"DL","flight_number":"6806"}],"flightNumber":"327","arrivalTime":"17:56:00","departureTime":"17:11:00"},{"airlineIata":"HA","arrivalIata":"HNL","departureIata":"KOA","codeshares":[{"airline_code":"DL","flight_number":"6841"},{"airline_code":"NH","flight_number":"7877"},{"airline_code":"PR","flight_number":"1027"},{"airline_code":"VA","flight_number":"5114"}],"flightNumber":"337","arrivalTime":"09:49:00","departureTime":"09:05:00"},{"airlineIata":"HA","arrivalIata":"HNL","departureIata":"KOA","codeshares":[{"airline_code":"AA","flight_number":"7888"},{"airline_code":"DL","flight_number":"6811"},{"airline_code":"KE","flight_number":"7828"},{"airline_code":"NH","flight_number":"5627"},{"airline_code":"UA","flight_number":"7794"}],"flightNumber":"347","arrivalTime":"17:15:00","departureTime":"16:30:00"},{"airlineIata":"HA","arrivalIata":"OGG","departureIata":"KOA","codeshares":[{"airline_code":"DL","flight_number":"6850"},{"airline_code":"UA","flight_number":"7872"}],"flightNumber":"349","arrivalTime":"10:01:00","departureTime":"09:26:00"},{"airlineIata":"HA","arrivalIata":"HNL","departureIata":"KOA","codeshares":[{"airline_code":"B6","flight_number":"5886"},{"airline_code":"DL","flight_number":"6833"},{"airline_code":"NH","flight_number":"5621"}],"flightNumber":"351","arrivalTime":"12:55:00","departureTime":"12:10:00"},{"airlineIata":"HA","arrivalIata":"HNL","departureIata":"KOA","codeshares":[{"airline_code":"CA","flight_number":"6984"},{"airline_code":"KE","flight_number":"7822"},{"airline_code":"NH","flight_number":"5629"},{"airline_code":"PR","flight_number":"1027"},{"airline_code":"VA","flight_number":"5114"}],"flightNumber":"367","arrivalTime":"10:27:00","departureTime":"09:43:00"},{"airlineIata":"HA","arrivalIata":"HNL","departureIata":"KOA","codeshares":[{"airline_code":"AA","flight_number":"7907"},{"airline_code":"DL","flight_number":"6829"},{"airline_code":"UA","flight_number":"7869"}],"flightNumber":"387","arrivalTime":"17:01:00","departureTime":"16:16:00"},{"airlineIata":"HA","arrivalIata":"HNL","departureIata":"KOA","codeshares":[{"airline_code":"KE","flight_number":"7838"},{"airline_code":"UA","flight_number":"7798"}],"flightNumber":"397","arrivalTime":"22:03:00","departureTime":"21:20:00"},{"airlineIata":"HA","arrivalIata":"HNL","departureIata":"KOA","codeshares":null,"flightNumber":"399","arrivalTime":"13:45:00","departureTime":"12:59:00"},{"airlineIata":"HA","arrivalIata":"HNL","departureIata":"KOA","codeshares":null,"flightNumber":"507","arrivalTime":"18:53:00","departureTime":"18:08:00"},{"airlineIata":"HA","arrivalIata":"HNL","departureIata":"KOA","codeshares":[{"airline_code":"AA","flight_number":"7931"},{"airline_code":"DL","flight_number":"6833"}],"flightNumber":"517","arrivalTime":"12:37:00","departureTime":"11:50:00"},{"airlineIata":"HA","arrivalIata":"HNL","departureIata":"KOA","codeshares":null,"flightNumber":"527","arrivalTime":"11:11:00","departureTime":"10:27:00"},{"airlineIata":"HA","arrivalIata":"HNL","departureIata":"KOA","codeshares":null,"flightNumber":"537","arrivalTime":"17:29:00","departureTime":"16:44:00"},{"airlineIata":"HA","arrivalIata":"HNL","departureIata":"KOA","codeshares":null,"flightNumber":"547","arrivalTime":"14:52:00","departureTime":"14:05:00"},{"airlineIata":"HA","arrivalIata":"HNL","departureIata":"KOA","codeshares":[{"airline_code":"NH","flight_number":"5619"},{"airline_code":"AA","flight_number":"7881"}],"flightNumber":"549","arrivalTime":"11:03:00","departureTime":"10:17:00"},{"airlineIata":"HA","arrivalIata":"HNL","departureIata":"KOA","codeshares":[{"airline_code":"UA","flight_number":"7798"}],"flightNumber":"577","arrivalTime":"22:08:00","departureTime":"21:25:00"},{"airlineIata":"HA","arrivalIata":"HNL","departureIata":"KOA","codeshares":null,"flightNumber":"587","arrivalTime":"10:53:00","departureTime":"10:09:00"},{"airlineIata":"HA","arrivalIata":"LIH","departureIata":"KOA","codeshares":null,"flightNumber":"599","arrivalTime":"10:36:00","departureTime":"09:38:00"},{"airlineIata":"HA","arrivalIata":"OGG","departureIata":"KOA","codeshares":null,"flightNumber":"641","arrivalTime":null,"departureTime":null},{"airlineIata":"HA","arrivalIata":"OAK","departureIata":"KOA","codeshares":null,"flightNumber":"66","arrivalTime":"23:40:00","departureTime":"15:30:00"},{"airlineIata":"HA","arrivalIata":"HNL","departureIata":"KOA","codeshares":null,"flightNumber":"8107","arrivalTime":null,"departureTime":null},{"airlineIata":"HA","arrivalIata":"HNL","departureIata":"KOA","codeshares":null,"flightNumber":"9061","arrivalTime":null,"departureTime":null},{"airlineIata":"HA","arrivalIata":"HNL","departureIata":"KOA","codeshares":null,"flightNumber":"9117","arrivalTime":null,"departureTime":null},{"airlineIata":"HA","arrivalIata":"LIH","departureIata":"KOA","codeshares":null,"flightNumber":"950","arrivalTime":null,"departureTime":null},{"airlineIata":"HA","arrivalIata":"HNL","departureIata":"KOA","codeshares":null,"flightNumber":"951","arrivalTime":null,"departureTime":null},{"airlineIata":"HA","arrivalIata":"HNL","departureIata":"KOA","codeshares":null,"flightNumber":"955","arrivalTime":null,"departureTime":null},{"airlineIata":"HA","arrivalIata":"OGG","departureIata":"KOA","codeshares":null,"flightNumber":"9961","arrivalTime":null,"departureTime":null},{"airlineIata":"K4","arrivalIata":"HNL","departureIata":"KOA","codeshares":null,"flightNumber":"2965","arrivalTime":null,"departureTime":null},{"airlineIata":"K4","arrivalIata":"LAX","departureIata":"KOA","codeshares":null,"flightNumber":"369","arrivalTime":null,"departureTime":null},{"airlineIata":"KH","arrivalIata":"HNL","departureIata":"KOA","codeshares":null,"flightNumber":"41","arrivalTime":null,"departureTime":null},{"airlineIata":"KH","arrivalIata":"HNL","departureIata":"KOA","codeshares":null,"flightNumber":"423","arrivalTime":null,"departureTime":null},{"airlineIata":"KH","arrivalIata":"HNL","departureIata":"KOA","codeshares":null,"flightNumber":"425","arrivalTime":null,"departureTime":null},{"airlineIata":"KH","arrivalIata":"HNL","departureIata":"KOA","codeshares":null,"flightNumber":"43","arrivalTime":null,"departureTime":null},{"airlineIata":"KH","arrivalIata":"HNL","departureIata":"KOA","codeshares":null,"flightNumber":"4403","arrivalTime":null,"departureTime":null},{"airlineIata":"KH","arrivalIata":"HNL","departureIata":"KOA","codeshares":null,"flightNumber":"4407","arrivalTime":null,"departureTime":null},{"airlineIata":"KH","arrivalIata":"HNL","departureIata":"KOA","codeshares":null,"flightNumber":"441","arrivalTime":null,"departureTime":null},{"airlineIata":"KH","arrivalIata":"HNL","departureIata":"KOA","codeshares":null,"flightNumber":"443","arrivalTime":null,"departureTime":null},{"airlineIata":"KH","arrivalIata":"HNL","departureIata":"KOA","codeshares":null,"flightNumber":"445","arrivalTime":null,"departureTime":null},{"airlineIata":"KH","arrivalIata":"HNL","departureIata":"KOA","codeshares":null,"flightNumber":"447","arrivalTime":null,"departureTime":null},{"airlineIata":"KH","arrivalIata":"HNL","departureIata":"KOA","codeshares":null,"flightNumber":"449","arrivalTime":null,"departureTime":null},{"airlineIata":"KH","arrivalIata":"HNL","departureIata":"KOA","codeshares":null,"flightNumber":"45","arrivalTime":null,"departureTime":null},{"airlineIata":"KH","arrivalIata":"HNL","departureIata":"KOA","codeshares":null,"flightNumber":"47","arrivalTime":null,"departureTime":null},{"airlineIata":"KH","arrivalIata":"HNL","departureIata":"KOA","codeshares":null,"flightNumber":"49","arrivalTime":null,"departureTime":null},{"airlineIata":"KH","arrivalIata":"ITO","departureIata":"KOA","codeshares":null,"flightNumber":"552","arrivalTime":null,"departureTime":null},{"airlineIata":"MW","arrivalIata":"MUE","departureIata":"KOA","codeshares":null,"flightNumber":"400","arrivalTime":null,"departureTime":null},{"airlineIata":"MW","arrivalIata":"JHM","departureIata":"KOA","codeshares":null,"flightNumber":"515","arrivalTime":"15:10:00","departureTime":"14:25:00"},{"airlineIata":"MW","arrivalIata":"JHM","departureIata":"KOA","codeshares":null,"flightNumber":"521","arrivalTime":"13:25:00","departureTime":"12:40:00"},{"airlineIata":"MW","arrivalIata":"JHM","departureIata":"KOA","codeshares":null,"flightNumber":"523","arrivalTime":"10:20:00","departureTime":"09:30:00"},{"airlineIata":"MW","arrivalIata":"OGG","departureIata":"KOA","codeshares":null,"flightNumber":"651","arrivalTime":"10:25:00","departureTime":"09:40:00"},{"airlineIata":"MW","arrivalIata":"OGG","departureIata":"KOA","codeshares":null,"flightNumber":"709","arrivalTime":"11:40:00","departureTime":"10:55:00"},{"airlineIata":"MW","arrivalIata":"MKK","departureIata":"KOA","codeshares":null,"flightNumber":"715","arrivalTime":"17:55:00","departureTime":"17:00:00"},{"airlineIata":"MW","arrivalIata":"OGG","departureIata":"KOA","codeshares":null,"flightNumber":"717","arrivalTime":"08:50:00","departureTime":"08:05:00"},{"airlineIata":"MW","arrivalIata":"OGG","departureIata":"KOA","codeshares":null,"flightNumber":"721","arrivalTime":"06:45:00","departureTime":"06:00:00"},{"airlineIata":"MW","arrivalIata":"OGG","departureIata":"KOA","codeshares":null,"flightNumber":"723","arrivalTime":"08:55:00","departureTime":"08:10:00"},{"airlineIata":"MW","arrivalIata":"MKK","departureIata":"KOA","codeshares":null,"flightNumber":"725","arrivalTime":"08:00:00","departureTime":"07:05:00"},{"airlineIata":"MW","arrivalIata":"OGG","departureIata":"KOA","codeshares":null,"flightNumber":"727","arrivalTime":"09:50:00","departureTime":"09:05:00"},{"airlineIata":"MW","arrivalIata":"OGG","departureIata":"KOA","codeshares":null,"flightNumber":"729","arrivalTime":"14:35:00","departureTime":"13:50:00"},{"airlineIata":"MW","arrivalIata":"OGG","departureIata":"KOA","codeshares":null,"flightNumber":"733","arrivalTime":"11:00:00","departureTime":"10:15:00"},{"airlineIata":"MW","arrivalIata":"OGG","departureIata":"KOA","codeshares":null,"flightNumber":"735","arrivalTime":"12:10:00","departureTime":"11:25:00"},{"airlineIata":"MW","arrivalIata":"OGG","departureIata":"KOA","codeshares":null,"flightNumber":"737","arrivalTime":"13:10:00","departureTime":"12:25:00"},{"airlineIata":"MW","arrivalIata":"OGG","departureIata":"KOA","codeshares":null,"flightNumber":"739","arrivalTime":"15:20:00","departureTime":"14:35:00"},{"airlineIata":"MW","arrivalIata":"OGG","departureIata":"KOA","codeshares":null,"flightNumber":"745","arrivalTime":"12:40:00","departureTime":"11:55:00"},{"airlineIata":"MW","arrivalIata":"MKK","departureIata":"KOA","codeshares":null,"flightNumber":"747","arrivalTime":"15:40:00","departureTime":"14:45:00"},{"airlineIata":"MW","arrivalIata":"OGG","departureIata":"KOA","codeshares":null,"flightNumber":"749","arrivalTime":"18:55:00","departureTime":"18:10:00"},{"airlineIata":"MW","arrivalIata":"OGG","departureIata":"KOA","codeshares":null,"flightNumber":"751","arrivalTime":"20:30:00","departureTime":"19:45:00"},{"airlineIata":"RV","arrivalIata":"YVR","departureIata":"KOA","codeshares":[{"airline_code":"AC","flight_number":"1958"}],"flightNumber":"1958","arrivalTime":"00:15:00","departureTime":"15:30:00"},{"airlineIata":"UA","arrivalIata":"LAX","departureIata":"KOA","codeshares":[{"airline_code":"AC","flight_number":"5235"},{"airline_code":"CM","flight_number":"8260"},{"airline_code":"LH","flight_number":"9381"}],"flightNumber":"1147","arrivalTime":"05:15:00","departureTime":"20:58:00"},{"airlineIata":"UA","arrivalIata":"LAX","departureIata":"KOA","codeshares":[{"airline_code":"AC","flight_number":"5906"},{"airline_code":"AV","flight_number":"2256"},{"airline_code":"CM","flight_number":"8110"}],"flightNumber":"1205","arrivalTime":"21:09:00","departureTime":"12:49:00"},{"airlineIata":"UA","arrivalIata":"SFO","departureIata":"KOA","codeshares":[{"airline_code":"CM","flight_number":"1801"}],"flightNumber":"1263","arrivalTime":"21:29:00","departureTime":"13:19:00"},{"airlineIata":"UA","arrivalIata":"SFO","departureIata":"KOA","codeshares":[{"airline_code":"CM","flight_number":"1164"},{"airline_code":"LH","flight_number":"9393"}],"flightNumber":"1724","arrivalTime":"05:25:00","departureTime":"21:28:00"},{"airlineIata":"UA","arrivalIata":"DEN","departureIata":"KOA","codeshares":null,"flightNumber":"1731","arrivalTime":"07:06:00","departureTime":"20:15:00"},{"airlineIata":"WP","arrivalIata":"HNL","departureIata":"KOA","codeshares":null,"flightNumber":"145","arrivalTime":null,"departureTime":null},{"airlineIata":"WP","arrivalIata":"HNL","departureIata":"KOA","codeshares":null,"flightNumber":"1803","arrivalTime":null,"departureTime":null},{"airlineIata":"WP","arrivalIata":"HNL","departureIata":"KOA","codeshares":null,"flightNumber":"263","arrivalTime":"08:43:00","departureTime":"07:46:00"},{"airlineIata":"WP","arrivalIata":"HNL","departureIata":"KOA","codeshares":null,"flightNumber":"265","arrivalTime":"20:51:00","departureTime":"19:56:00"},{"airlineIata":"WP","arrivalIata":"HNL","departureIata":"KOA","codeshares":[{"airline_code":"UA","flight_number":"7748"}],"flightNumber":"81","arrivalTime":"09:12:00","departureTime":"08:17:00"},{"airlineIata":"WP","arrivalIata":"HNL","departureIata":"KOA","codeshares":[{"airline_code":"UA","flight_number":"7749"}],"flightNumber":"83","arrivalTime":"13:04:00","departureTime":"12:09:00"},{"airlineIata":"WP","arrivalIata":"HNL","departureIata":"KOA","codeshares":[{"airline_code":"UA","flight_number":"7750"}],"flightNumber":"85","arrivalTime":"15:12:00","departureTime":"14:17:00"},{"airlineIata":"WP","arrivalIata":"HNL","departureIata":"KOA","codeshares":[{"airline_code":"UA","flight_number":"7751"}],"flightNumber":"89","arrivalTime":"18:11:00","departureTime":"17:16:00"},{"airlineIata":"WP","arrivalIata":"HNL","departureIata":"KOA","codeshares":null,"flightNumber":"93","arrivalTime":"10:26:00","departureTime":"09:32:00"},{"airlineIata":"WP","arrivalIata":"HNL","departureIata":"KOA","codeshares":null,"flightNumber":"99","arrivalTime":"08:55:00","departureTime":"07:58:00"},{"airlineIata":"WS","arrivalIata":"YVR","departureIata":"KOA","codeshares":[{"airline_code":"KL","flight_number":"9677"}],"flightNumber":"1883","arrivalTime":"06:43:00","departureTime":"22:00:00"}]