[{"airlineIata":"FY","arrivalIata":"PEN","departureIata":"KUA","codeshares":[{"airline_code":"MH","flight_number":"5292"}],"flightNumber":"1034","arrivalTime":"16:50:00","departureTime":"15:20:00"},{"airlineIata":"FY","arrivalIata":"SIN","departureIata":"KUA","codeshares":[{"airline_code":"MH","flight_number":"5461"}],"flightNumber":"3573","arrivalTime":"14:10:00","departureTime":"13:05:00"},{"airlineIata":"MH","arrivalIata":"KUL","departureIata":"KUA","codeshares":[{"airline_code":"EK","flight_number":"3343"}],"flightNumber":"1263","arrivalTime":"07:25:00","departureTime":"06:40:00"},{"airlineIata":"MH","arrivalIata":"KUL","departureIata":"KUA","codeshares":[{"airline_code":"EK","flight_number":"3345"}],"flightNumber":"1269","arrivalTime":"11:00:00","departureTime":"10:15:00"},{"airlineIata":"MH","arrivalIata":"KUL","departureIata":"KUA","codeshares":[{"airline_code":"EK","flight_number":"3347"},{"airline_code":"EY","flight_number":"4194"},{"airline_code":"JL","flight_number":"7962"}],"flightNumber":"1281","arrivalTime":"20:30:00","departureTime":"19:45:00"}]