[{"airlineIata":"5Y","arrivalIata":"LAX","departureIata":"VPS","codeshares":null,"flightNumber":"8574","arrivalTime":null,"departureTime":null},{"airlineIata":"LL","arrivalIata":"PVD","departureIata":"VPS","codeshares":null,"flightNumber":"642","arrivalTime":null,"departureTime":null},{"airlineIata":"DL","arrivalIata":"ATL","departureIata":"VPS","codeshares":null,"flightNumber":"2517","arrivalTime":"07:16:00","departureTime":"05:05:00"},{"airlineIata":"DL","arrivalIata":"ATL","departureIata":"VPS","codeshares":null,"flightNumber":"2519","arrivalTime":"09:29:00","departureTime":"07:15:00"},{"airlineIata":"DL","arrivalIata":"ATL","departureIata":"VPS","codeshares":null,"flightNumber":"2949","arrivalTime":"09:44:00","departureTime":"07:30:00"},{"airlineIata":"EV","arrivalIata":"TYS","departureIata":"VPS","codeshares":[{"airline_code":"UA","flight_number":"2488"}],"flightNumber":"2488","arrivalTime":null,"departureTime":null},{"airlineIata":"EV","arrivalIata":"DFW","departureIata":"VPS","codeshares":[{"airline_code":"BA","flight_number":"1894"},{"airline_code":"AA","flight_number":"2815"}],"flightNumber":"2815","arrivalTime":"11:43:00","departureTime":"09:35:00"},{"airlineIata":"EV","arrivalIata":"DFW","departureIata":"VPS","codeshares":[{"airline_code":"BA","flight_number":"4425"},{"airline_code":"AA","flight_number":"2850"}],"flightNumber":"2850","arrivalTime":"21:13:00","departureTime":"19:03:00"},{"airlineIata":"EV","arrivalIata":"IAH","departureIata":"VPS","codeshares":[{"airline_code":"AC","flight_number":"3223"},{"airline_code":"CM","flight_number":"5507"},{"airline_code":"LH","flight_number":"8684"},{"airline_code":"UA","flight_number":"3941"}],"flightNumber":"3941","arrivalTime":"17:00:00","departureTime":"15:05:00"},{"airlineIata":"EV","arrivalIata":"IAH","departureIata":"VPS","codeshares":[{"airline_code":"AC","flight_number":"3219"},{"airline_code":"CM","flight_number":"5471"},{"airline_code":"UA","flight_number":"4345"}],"flightNumber":"4345","arrivalTime":"07:49:00","departureTime":"06:00:00"},{"airlineIata":"EV","arrivalIata":"ATL","departureIata":"VPS","codeshares":[{"airline_code":"DL","flight_number":"5281"}],"flightNumber":"5281","arrivalTime":"10:41:00","departureTime":"08:25:00"},{"airlineIata":"G4","arrivalIata":"CVG","departureIata":"VPS","codeshares":null,"flightNumber":"1343","arrivalTime":"11:24:00","departureTime":"08:44:00"},{"airlineIata":"G4","arrivalIata":"BLV","departureIata":"VPS","codeshares":null,"flightNumber":"1352","arrivalTime":"10:16:00","departureTime":"08:26:00"},{"airlineIata":"G4","arrivalIata":"BLV","departureIata":"VPS","codeshares":null,"flightNumber":"1902","arrivalTime":"09:15:00","departureTime":"07:30:00"},{"airlineIata":"G4","arrivalIata":"MEM","departureIata":"VPS","codeshares":null,"flightNumber":"1904","arrivalTime":"08:30:00","departureTime":"07:00:00"},{"airlineIata":"G4","arrivalIata":"OKC","departureIata":"VPS","codeshares":null,"flightNumber":"1908","arrivalTime":"10:35:00","departureTime":"08:20:00"},{"airlineIata":"G4","arrivalIata":"MCI","departureIata":"VPS","codeshares":null,"flightNumber":"1914","arrivalTime":"08:36:00","departureTime":"06:30:00"},{"airlineIata":"G4","arrivalIata":"PIA","departureIata":"VPS","codeshares":null,"flightNumber":"1916","arrivalTime":"09:53:00","departureTime":"08:00:00"},{"airlineIata":"G4","arrivalIata":"CLE","departureIata":"VPS","codeshares":null,"flightNumber":"1948","arrivalTime":"10:33:00","departureTime":"07:32:00"},{"airlineIata":"G4","arrivalIata":"IND","departureIata":"VPS","codeshares":null,"flightNumber":"1970","arrivalTime":null,"departureTime":null},{"airlineIata":"G4","arrivalIata":"EWR","departureIata":"VPS","codeshares":null,"flightNumber":"1990","arrivalTime":"10:00:00","departureTime":"06:30:00"},{"airlineIata":"G4","arrivalIata":"AUS","departureIata":"VPS","codeshares":null,"flightNumber":"1992","arrivalTime":"09:59:00","departureTime":"08:00:00"},{"airlineIata":"G4","arrivalIata":"SGF","departureIata":"VPS","codeshares":null,"flightNumber":"2912","arrivalTime":"10:01:00","departureTime":"08:00:00"},{"airlineIata":"G4","arrivalIata":"MCI","departureIata":"VPS","codeshares":null,"flightNumber":"2914","arrivalTime":"10:18:00","departureTime":"08:00:00"},{"airlineIata":"G4","arrivalIata":"MEM","departureIata":"VPS","codeshares":null,"flightNumber":"5743","arrivalTime":null,"departureTime":null},{"airlineIata":"G4","arrivalIata":"RDU","departureIata":"VPS","codeshares":null,"flightNumber":"8063","arrivalTime":null,"departureTime":null},{"airlineIata":"G4","arrivalIata":"PIE","departureIata":"VPS","codeshares":null,"flightNumber":"9228","arrivalTime":null,"departureTime":null},{"airlineIata":"G4","arrivalIata":"TPA","departureIata":"VPS","codeshares":null,"flightNumber":"9233","arrivalTime":null,"departureTime":null},{"airlineIata":"OH","arrivalIata":"CLT","departureIata":"VPS","codeshares":[{"airline_code":"AA","flight_number":"5157"}],"flightNumber":"5157","arrivalTime":"10:15:00","departureTime":"07:29:00"},{"airlineIata":"OH","arrivalIata":"CLT","departureIata":"VPS","codeshares":[{"airline_code":"AA","flight_number":"5431"}],"flightNumber":"5431","arrivalTime":"10:42:00","departureTime":"08:00:00"},{"airlineIata":"OH","arrivalIata":"CLT","departureIata":"VPS","codeshares":[{"airline_code":"AA","flight_number":"5709"}],"flightNumber":"5709","arrivalTime":"08:40:00","departureTime":"06:05:00"},{"airlineIata":"MQ","arrivalIata":"DFW","departureIata":"VPS","codeshares":[{"airline_code":"AA","flight_number":"3266"}],"flightNumber":"3266","arrivalTime":"10:10:00","departureTime":"08:01:00"},{"airlineIata":"MQ","arrivalIata":"DFW","departureIata":"VPS","codeshares":[{"airline_code":"AA","flight_number":"3280"}],"flightNumber":"3280","arrivalTime":"08:10:00","departureTime":"05:58:00"},{"airlineIata":"MQ","arrivalIata":"DFW","departureIata":"VPS","codeshares":[{"airline_code":"AA","flight_number":"3533"}],"flightNumber":"3533","arrivalTime":"08:04:00","departureTime":"05:55:00"},{"airlineIata":"LF","arrivalIata":"LIT","departureIata":"VPS","codeshares":null,"flightNumber":"161","arrivalTime":null,"departureTime":null},{"airlineIata":"LF","arrivalIata":"BWG","departureIata":"VPS","codeshares":null,"flightNumber":"2005","arrivalTime":"13:50:00","departureTime":"12:00:00"},{"airlineIata":"YV","arrivalIata":"IAH","departureIata":"VPS","codeshares":[{"airline_code":"AC","flight_number":"3782"},{"airline_code":"CM","flight_number":"5471"},{"airline_code":"UA","flight_number":"6338"}],"flightNumber":"6338","arrivalTime":"07:54:00","departureTime":"06:05:00"},{"airlineIata":"G4","arrivalIata":"CVG","departureIata":"VPS","codeshares":null,"flightNumber":"1900","arrivalTime":"09:47:00","departureTime":"07:00:00"},{"airlineIata":"G4","arrivalIata":"TYS","departureIata":"VPS","codeshares":null,"flightNumber":"1906","arrivalTime":"09:19:00","departureTime":"07:00:00"}]